[{"cdCargo": 7, "cargo": "DEPUTADO ESTADUAL", "id": 10001622770, "numero": 12888, "nomeUrna": "ANT\u00d4NIA DO LANCHE", "situacao": "APTO", "partido": "PDT"}, {"cdCargo": 7, "cargo": "DEPUTADO ESTADUAL", "id": 10001635543, "numero": 10333, "nomeUrna": "GEANA FERREIRA", "situacao": "APTO", "partido": "REPUBLICANOS"}, {"cdCargo": 6, "cargo": "DEPUTADO FEDERAL", "id": 10001723625, "numero": 2022, "nomeUrna": "LUANA ARA\u00daJO", "situacao": "APTO", "partido": "PSC"}, {"cdCargo": 7, "cargo": "DEPUTADO ESTADUAL", "id": 10001642314, "numero": 15192, "nomeUrna": "VANDERLI FERREIRA", "situacao": "APTO", "partido": "MDB"}, {"cdCargo": 7, "cargo": "DEPUTADO ESTADUAL", "id": 10001623553, "numero": 44888, "nomeUrna": "ALDENORA SALES", "situacao": "APTO", "partido": "UNI\u00c3O"}, {"cdCargo": 6, "cargo": "DEPUTADO FEDERAL", "id": 10001738921, "numero": 2020, "nomeUrna": "JEC\u00c9 MECANICO", "situacao": "APTO", "partido": "PSC"}, {"cdCargo": 7, "cargo": "DEPUTADO ESTADUAL", "id": 10001642313, "numero": 15555, "nomeUrna": "TANIZIO S\u00c1", "situacao": "APTO", "partido": "MDB"}, {"cdCargo": 7, "cargo": "DEPUTADO ESTADUAL", "id": 10001649317, "numero": 22023, "nomeUrna": "PASTORA OTACILIA SILVA", "situacao": "APTO", "partido": "PL"}, {"cdCargo": 7, "cargo": "DEPUTADO ESTADUAL", "id": 10001726045, "numero": 51006, "nomeUrna": "ZILIANE LIMA", "situacao": "APTO", "partido": "PATRIOTA"}, {"cdCargo": 10, "cargo": "2\u00ba SUPLENTE", "id": 10001643445, "numero": 400, "nomeUrna": "CORONEL ANAST\u00c1CIO", "situacao": "APTO", "partido": "PSB"}, {"cdCargo": 7, "cargo": "DEPUTADO ESTADUAL", "id": 10001635542, "numero": 10567, "nomeUrna": "JAIRO CARVALHO", "situacao": "APTO", "partido": "REPUBLICANOS"}, {"cdCargo": 6, "cargo": "DEPUTADO FEDERAL", "id": 10001655721, "numero": 1900, "nomeUrna": "ARTUR NETO", "situacao": "APTO", "partido": "PODE"}, {"cdCargo": 7, "cargo": "DEPUTADO ESTADUAL", "id": 10001717434, "numero": 27316, "nomeUrna": "CABIDE", "situacao": "APTO", "partido": "DC"}, {"cdCargo": 6, "cargo": "DEPUTADO FEDERAL", "id": 10001595345, "numero": 1818, "nomeUrna": "NINAWA HUNI KUI", "situacao": "APTO", "partido": "REDE"}, {"cdCargo": 6, "cargo": "DEPUTADO FEDERAL", "id": 10001716347, "numero": 4533, "nomeUrna": "Z\u00c9 PREGO", "situacao": "APTO", "partido": "PSDB"}, {"cdCargo": 7, "cargo": "DEPUTADO ESTADUAL", "id": 10001649330, "numero": 22345, "nomeUrna": "Z\u00c9 LOPES", "situacao": "APTO", "partido": "PL"}, {"cdCargo": 6, "cargo": "DEPUTADO FEDERAL", "id": 10001619993, "numero": 1010, "nomeUrna": "ROBERTO DUARTE", "situacao": "APTO", "partido": "REPUBLICANOS"}, {"cdCargo": 7, "cargo": "DEPUTADO ESTADUAL", "id": 10001623551, "numero": 44012, "nomeUrna": "ROSIMEIRY ARAUJO", "situacao": "APTO", "partido": "UNI\u00c3O"}, {"cdCargo": 7, "cargo": "DEPUTADO ESTADUAL", "id": 10001670862, "numero": 51123, "nomeUrna": "GIS ARAUJO", "situacao": "APTO", "partido": "PATRIOTA"}, {"cdCargo": 7, "cargo": "DEPUTADO ESTADUAL", "id": 10001606513, "numero": 36500, "nomeUrna": "MARIA EUL\u00c1LIA", "situacao": "APTO", "partido": "AGIR"}, {"cdCargo": 6, "cargo": "DEPUTADO FEDERAL", "id": 10001655720, "numero": 1919, "nomeUrna": "RODRIGO DAMASCENO", "situacao": "APTO", "partido": "PODE"}, {"cdCargo": 6, "cargo": "DEPUTADO FEDERAL", "id": 10001655354, "numero": 3322, "nomeUrna": "JOS\u00c9 RIBAMAR", "situacao": "APTO", "partido": "PMN"}, {"cdCargo": 7, "cargo": "DEPUTADO ESTADUAL", "id": 10001606212, "numero": 90234, "nomeUrna": "LETICIA YAWANAW\u00c1", "situacao": "APTO", "partido": "PROS"}, {"cdCargo": 7, "cargo": "DEPUTADO ESTADUAL", "id": 10001601445, "numero": 55789, "nomeUrna": "ESPERIDI\u00c3O DOS TRANSPORTES", "situacao": "APTO", "partido": "PSD"}, {"cdCargo": 7, "cargo": "DEPUTADO ESTADUAL", "id": 10001642311, "numero": 15888, "nomeUrna": "GILBERTO DINIZ", "situacao": "APTO", "partido": "MDB"}, {"cdCargo": 7, "cargo": "DEPUTADO ESTADUAL", "id": 10001723802, "numero": 23333, "nomeUrna": "JAILSON ALMEIDA", "situacao": "APTO", "partido": "CIDADANIA"}, {"cdCargo": 7, "cargo": "DEPUTADO ESTADUAL", "id": 10001606209, "numero": 90999, "nomeUrna": "BETO FIGUEIREDO", "situacao": "APTO", "partido": "PROS"}, {"cdCargo": 7, "cargo": "DEPUTADO ESTADUAL", "id": 10001717433, "numero": 27012, "nomeUrna": "MANOEL IZO", "situacao": "APTO", "partido": "DC"}, {"cdCargo": 7, "cargo": "DEPUTADO ESTADUAL", "id": 10001643313, "numero": 40800, "nomeUrna": "RIDERSON ROCHA", "situacao": "APTO", "partido": "PSB"}, {"cdCargo": 6, "cargo": "DEPUTADO FEDERAL", "id": 10001619995, "numero": 1023, "nomeUrna": "KATIANNY ARA\u00daJO", "situacao": "APTO", "partido": "REPUBLICANOS"}, {"cdCargo": 7, "cargo": "DEPUTADO ESTADUAL", "id": 10001606201, "numero": 90147, "nomeUrna": "PROFESSORA MARISSANTA", "situacao": "APTO", "partido": "PROS"}, {"cdCargo": 6, "cargo": "DEPUTADO FEDERAL", "id": 10001606126, "numero": 9011, "nomeUrna": "CABRAL", "situacao": "APTO", "partido": "PROS"}, {"cdCargo": 7, "cargo": "DEPUTADO ESTADUAL", "id": 10001601430, "numero": 55888, "nomeUrna": "EDUARDO RIBEIRO", "situacao": "APTO", "partido": "PSD"}, {"cdCargo": 7, "cargo": "DEPUTADO ESTADUAL", "id": 10001606217, "numero": 90000, "nomeUrna": "RAIMUNDINHO DA SAUDE", "situacao": "APTO", "partido": "PROS"}, {"cdCargo": 9, "cargo": "1\u00ba SUPLENTE", "id": 10001714548, "numero": 444, "nomeUrna": "GEMIL JUNIOR", "situacao": "APTO", "partido": "UNI\u00c3O"}, {"cdCargo": 6, "cargo": "DEPUTADO FEDERAL", "id": 10001614245, "numero": 3603, "nomeUrna": "NILVA DANIEL", "situacao": "APTO", "partido": "AGIR"}, {"cdCargo": 7, "cargo": "DEPUTADO ESTADUAL", "id": 10001635768, "numero": 13555, "nomeUrna": "CARLOS GOMES", "situacao": "APTO", "partido": "PT"}, {"cdCargo": 7, "cargo": "DEPUTADO ESTADUAL", "id": 10001726047, "numero": 40004, "nomeUrna": "NEURA VILA NOVA", "situacao": "APTO", "partido": "PSB"}, {"cdCargo": 7, "cargo": "DEPUTADO ESTADUAL", "id": 10001723800, "numero": 45121, "nomeUrna": "LUIZ GONZAGA", "situacao": "APTO", "partido": "PSDB"}, {"cdCargo": 7, "cargo": "DEPUTADO ESTADUAL", "id": 10001635774, "numero": 65650, "nomeUrna": "EDY BASTOS", "situacao": "APTO", "partido": "PC do B"}, {"cdCargo": 7, "cargo": "DEPUTADO ESTADUAL", "id": 10001606494, "numero": 36001, "nomeUrna": "FRANCISCO PINTO", "situacao": "APTO", "partido": "AGIR"}, {"cdCargo": 4, "cargo": "VICE-GOVERNADOR", "id": 10001601557, "numero": 55, "nomeUrna": "TOTA FILHO", "situacao": "APTO", "partido": "PSD"}, {"cdCargo": 7, "cargo": "DEPUTADO ESTADUAL", "id": 10001650028, "numero": 19223, "nomeUrna": "HERICA GRANZOTTO", "situacao": "APTO", "partido": "PODE"}, {"cdCargo": 7, "cargo": "DEPUTADO ESTADUAL", "id": 10001601428, "numero": 55122, "nomeUrna": "MARCIO BERNARDO", "situacao": "APTO", "partido": "PSD"}, {"cdCargo": 7, "cargo": "DEPUTADO ESTADUAL", "id": 10001623547, "numero": 44123, "nomeUrna": "ANTONIO PEDRO", "situacao": "APTO", "partido": "UNI\u00c3O"}, {"cdCargo": 9, "cargo": "1\u00ba SUPLENTE", "id": 10001601616, "numero": 900, "nomeUrna": "SOLINO MATOS", "situacao": "APTO", "partido": "AVANTE"}, {"cdCargo": 6, "cargo": "DEPUTADO FEDERAL", "id": 10001621649, "numero": 1100, "nomeUrna": "JOS\u00c9 ADRIANO", "situacao": "APTO", "partido": "PP"}, {"cdCargo": 7, "cargo": "DEPUTADO ESTADUAL", "id": 10001643317, "numero": 40111, "nomeUrna": "MANOEL ALMEIDA", "situacao": "APTO", "partido": "PSB"}, {"cdCargo": 10, "cargo": "2\u00ba SUPLENTE", "id": 10001606583, "numero": 364, "nomeUrna": "IVANA MOURA", "situacao": "APTO", "partido": "AGIR"}, {"cdCargo": 6, "cargo": "DEPUTADO FEDERAL", "id": 10001723626, "numero": 2000, "nomeUrna": "SGT CARLOS TANACA", "situacao": "APTO", "partido": "PSC"}, {"cdCargo": 6, "cargo": "DEPUTADO FEDERAL", "id": 10001621643, "numero": 1101, "nomeUrna": "SOCORRO NERI", "situacao": "APTO", "partido": "PP"}, {"cdCargo": 7, "cargo": "DEPUTADO ESTADUAL", "id": 10001643320, "numero": 40900, "nomeUrna": "SUELEN MOTA", "situacao": "APTO", "partido": "PSB"}, {"cdCargo": 7, "cargo": "DEPUTADO ESTADUAL", "id": 10001723799, "numero": 45777, "nomeUrna": "PROF PAULO HENRIQUE", "situacao": "APTO", "partido": "PSDB"}, {"cdCargo": 7, "cargo": "DEPUTADO ESTADUAL", "id": 10001635777, "numero": 65123, "nomeUrna": "EDVALDO MAGALH\u00c3ES", "situacao": "APTO", "partido": "PC do B"}, {"cdCargo": 7, "cargo": "DEPUTADO ESTADUAL", "id": 10001622763, "numero": 12333, "nomeUrna": "PEDRO LONGO", "situacao": "APTO", "partido": "PDT"}, {"cdCargo": 7, "cargo": "DEPUTADO ESTADUAL", "id": 10001595348, "numero": 50888, "nomeUrna": "HERILTON FONTENELE", "situacao": "APTO", "partido": "PSOL"}, {"cdCargo": 6, "cargo": "DEPUTADO FEDERAL", "id": 10001614196, "numero": 1314, "nomeUrna": "IREN\u00cd UCH\u00d4A", "situacao": "APTO", "partido": "PT"}, {"cdCargo": 7, "cargo": "DEPUTADO ESTADUAL", "id": 10001670858, "numero": 51000, "nomeUrna": "MAURICIO DO CHAL\u00c9", "situacao": "APTO", "partido": "PATRIOTA"}, {"cdCargo": 7, "cargo": "DEPUTADO ESTADUAL", "id": 10001723785, "numero": 45111, "nomeUrna": "ER\u00c9 MORAES", "situacao": "APTO", "partido": "PSDB"}, {"cdCargo": 7, "cargo": "DEPUTADO ESTADUAL", "id": 10001595361, "numero": 50055, "nomeUrna": "RAIMUNDO ARA\u00daJO", "situacao": "APTO", "partido": "PSOL"}, {"cdCargo": 7, "cargo": "DEPUTADO ESTADUAL", "id": 10001670868, "numero": 51007, "nomeUrna": "PENINHA MAGALHAES", "situacao": "APTO", "partido": "PATRIOTA"}, {"cdCargo": 7, "cargo": "DEPUTADO ESTADUAL", "id": 10001643853, "numero": 77010, "nomeUrna": "ANA PAULA HONORATO", "situacao": "APTO", "partido": "SOLIDARIEDADE"}, {"cdCargo": 4, "cargo": "VICE-GOVERNADOR", "id": 10001616168, "numero": 13, "nomeUrna": "MARCUS ALEXANDRE", "situacao": "APTO", "partido": "PT"}, {"cdCargo": 7, "cargo": "DEPUTADO ESTADUAL", "id": 10001643856, "numero": 77526, "nomeUrna": "PAULO MACIEL", "situacao": "APTO", "partido": "SOLIDARIEDADE"}, {"cdCargo": 7, "cargo": "DEPUTADO ESTADUAL", "id": 10001643326, "numero": 40999, "nomeUrna": "AUGUSTO HENRIQUE", "situacao": "APTO", "partido": "PSB"}, {"cdCargo": 7, "cargo": "DEPUTADO ESTADUAL", "id": 10001601426, "numero": 55236, "nomeUrna": "ISAAC PIY\u00c3KO", "situacao": "APTO", "partido": "PSD"}, {"cdCargo": 7, "cargo": "DEPUTADO ESTADUAL", "id": 10001601422, "numero": 55123, "nomeUrna": "JEFRSON MENDON\u00c7A", "situacao": "APTO", "partido": "PSD"}, {"cdCargo": 6, "cargo": "DEPUTADO FEDERAL", "id": 10001655724, "numero": 1933, "nomeUrna": "MARCELO BIMBI", "situacao": "APTO", "partido": "PODE"}, {"cdCargo": 7, "cargo": "DEPUTADO ESTADUAL", "id": 10001717429, "numero": 27456, "nomeUrna": "EDEMILDES PAULINO", "situacao": "APTO", "partido": "DC"}, {"cdCargo": 7, "cargo": "DEPUTADO ESTADUAL", "id": 10001595358, "numero": 50444, "nomeUrna": "AMANDA SOUZA", "situacao": "APTO", "partido": "PSOL"}, {"cdCargo": 7, "cargo": "DEPUTADO ESTADUAL", "id": 10001635773, "numero": 13133, "nomeUrna": "SIDILENE LIMA", "situacao": "APTO", "partido": "PT"}, {"cdCargo": 7, "cargo": "DEPUTADO ESTADUAL", "id": 10001606500, "numero": 36555, "nomeUrna": "VAGNER SILVA", "situacao": "APTO", "partido": "AGIR"}, {"cdCargo": 7, "cargo": "DEPUTADO ESTADUAL", "id": 10001643328, "numero": 40043, "nomeUrna": "PROFESSORA CRIS NOGUEIRA", "situacao": "APTO", "partido": "PSB"}, {"cdCargo": 5, "cargo": "SENADOR", "id": 10001643544, "numero": 131, "nomeUrna": "NAZAR\u00c9 ARA\u00daJO", "situacao": "APTO", "partido": "PT"}, {"cdCargo": 6, "cargo": "DEPUTADO FEDERAL", "id": 10001614198, "numero": 1300, "nomeUrna": "MARIA SANTIAGO", "situacao": "APTO", "partido": "PT"}, {"cdCargo": 7, "cargo": "DEPUTADO ESTADUAL", "id": 10001601433, "numero": 55333, "nomeUrna": "ROMANO GOUVEA", "situacao": "APTO", "partido": "PSD"}, {"cdCargo": 7, "cargo": "DEPUTADO ESTADUAL", "id": 10001635783, "numero": 13500, "nomeUrna": "SALIM MANASFI", "situacao": "APTO", "partido": "PT"}, {"cdCargo": 6, "cargo": "DEPUTADO FEDERAL", "id": 10001717500, "numero": 2929, "nomeUrna": "MARIA IEDA", "situacao": "APTO", "partido": "PCO"}, {"cdCargo": 6, "cargo": "DEPUTADO FEDERAL", "id": 10001614195, "numero": 1313, "nomeUrna": "FRANCIMAR FERNANDES", "situacao": "APTO", "partido": "PT"}, {"cdCargo": 7, "cargo": "DEPUTADO ESTADUAL", "id": 10001643315, "numero": 40222, "nomeUrna": "ADAILTON CRUZ", "situacao": "APTO", "partido": "PSB"}, {"cdCargo": 7, "cargo": "DEPUTADO ESTADUAL", "id": 10001606502, "numero": 36946, "nomeUrna": "ADALBERTO ALMEIDA", "situacao": "APTO", "partido": "AGIR"}, {"cdCargo": 5, "cargo": "SENADOR", "id": 10001643706, "numero": 222, "nomeUrna": "MARCIA BITTAR", "situacao": "APTO", "partido": "PL"}, {"cdCargo": 7, "cargo": "DEPUTADO ESTADUAL", "id": 10001635763, "numero": 13234, "nomeUrna": "JO\u00c3OZINHO", "situacao": "APTO", "partido": "PT"}, {"cdCargo": 7, "cargo": "DEPUTADO ESTADUAL", "id": 10001736584, "numero": 11022, "nomeUrna": "NAZAR\u00c9 SOUSA", "situacao": "APTO", "partido": "PP"}, {"cdCargo": 6, "cargo": "DEPUTADO FEDERAL", "id": 10001613550, "numero": 1331, "nomeUrna": "LEO DE BRITO", "situacao": "APTO", "partido": "PT"}, {"cdCargo": 7, "cargo": "DEPUTADO ESTADUAL", "id": 10001606219, "numero": 90300, "nomeUrna": "DR. SAID SANTOS", "situacao": "APTO", "partido": "PROS"}, {"cdCargo": 7, "cargo": "DEPUTADO ESTADUAL", "id": 10001649306, "numero": 22022, "nomeUrna": "AZEVEDO", "situacao": "APTO", "partido": "PL"}, {"cdCargo": 6, "cargo": "DEPUTADO FEDERAL", "id": 10001621647, "numero": 1123, "nomeUrna": "DR NOGUEIRA", "situacao": "APTO", "partido": "PP"}, {"cdCargo": 7, "cargo": "DEPUTADO ESTADUAL", "id": 10001606507, "numero": 36398, "nomeUrna": "ZUILA DOM\u00c9STICA", "situacao": "APTO", "partido": "AGIR"}, {"cdCargo": 6, "cargo": "DEPUTADO FEDERAL", "id": 10001655719, "numero": 1920, "nomeUrna": "LOY REGO", "situacao": "APTO", "partido": "PODE"}, {"cdCargo": 7, "cargo": "DEPUTADO ESTADUAL", "id": 10001606213, "numero": 90888, "nomeUrna": "OSDENIR SANTOS", "situacao": "APTO", "partido": "PROS"}, {"cdCargo": 7, "cargo": "DEPUTADO ESTADUAL", "id": 10001723797, "numero": 23789, "nomeUrna": "ADENILSON DUAM", "situacao": "APTO", "partido": "CIDADANIA"}, {"cdCargo": 7, "cargo": "DEPUTADO ESTADUAL", "id": 10001643437, "numero": 11211, "nomeUrna": "TENENTE JARDIM", "situacao": "APTO", "partido": "PP"}, {"cdCargo": 6, "cargo": "DEPUTADO FEDERAL", "id": 10001622407, "numero": 1222, "nomeUrna": "RALPH FERNANDES", "situacao": "APTO", "partido": "PDT"}, {"cdCargo": 6, "cargo": "DEPUTADO FEDERAL", "id": 10001670806, "numero": 1800, "nomeUrna": "IUNA CHAVES", "situacao": "APTO", "partido": "REDE"}, {"cdCargo": 7, "cargo": "DEPUTADO ESTADUAL", "id": 10001622769, "numero": 12555, "nomeUrna": "DR. MICHELLE MELO", "situacao": "APTO", "partido": "PDT"}, {"cdCargo": 7, "cargo": "DEPUTADO ESTADUAL", "id": 10001595352, "numero": 50123, "nomeUrna": "MARQUINHO TCHUCKA S MOTOS", "situacao": "APTO", "partido": "PSOL"}, {"cdCargo": 7, "cargo": "DEPUTADO ESTADUAL", "id": 10001643430, "numero": 11000, "nomeUrna": "GABRIEL POLESI", "situacao": "APTO", "partido": "PP"}, {"cdCargo": 7, "cargo": "DEPUTADO ESTADUAL", "id": 10001623534, "numero": 44527, "nomeUrna": "CANTOR IZA\u00cdAS LIMA", "situacao": "APTO", "partido": "UNI\u00c3O"}, {"cdCargo": 7, "cargo": "DEPUTADO ESTADUAL", "id": 10001622778, "numero": 12247, "nomeUrna": "ROGGER WINS", "situacao": "APTO", "partido": "PDT"}, {"cdCargo": 7, "cargo": "DEPUTADO ESTADUAL", "id": 10001723792, "numero": 45008, "nomeUrna": "APARECIDA CIDINHA", "situacao": "APTO", "partido": "PSDB"}, {"cdCargo": 7, "cargo": "DEPUTADO ESTADUAL", "id": 10001723801, "numero": 23777, "nomeUrna": "NENO", "situacao": "APTO", "partido": "CIDADANIA"}, {"cdCargo": 6, "cargo": "DEPUTADO FEDERAL", "id": 10001655718, "numero": 1909, "nomeUrna": "IZABELLE ARA\u00daJO", "situacao": "APTO", "partido": "PODE"}, {"cdCargo": 7, "cargo": "DEPUTADO ESTADUAL", "id": 10001635765, "numero": 43700, "nomeUrna": "ANGELINO DO PANDEIRO", "situacao": "APTO", "partido": "PV"}, {"cdCargo": 7, "cargo": "DEPUTADO ESTADUAL", "id": 10001717431, "numero": 27111, "nomeUrna": "JANAINA DA BAIXA VERDE", "situacao": "APTO", "partido": "DC"}, {"cdCargo": 7, "cargo": "DEPUTADO ESTADUAL", "id": 10001601444, "numero": 55556, "nomeUrna": "KEKEL MENEZES", "situacao": "APTO", "partido": "PSD"}, {"cdCargo": 7, "cargo": "DEPUTADO ESTADUAL", "id": 10001601431, "numero": 55999, "nomeUrna": "TENENTE CORONEL AGLEISON", "situacao": "APTO", "partido": "PSD"}, {"cdCargo": 7, "cargo": "DEPUTADO ESTADUAL", "id": 10001606203, "numero": 90700, "nomeUrna": "MARIA EUNICE", "situacao": "APTO", "partido": "PROS"}, {"cdCargo": 7, "cargo": "DEPUTADO ESTADUAL", "id": 10001595349, "numero": 50222, "nomeUrna": "NOVA S", "situacao": "APTO", "partido": "PSOL"}, {"cdCargo": 7, "cargo": "DEPUTADO ESTADUAL", "id": 10001643327, "numero": 40007, "nomeUrna": "HALISSON RODRIGO", "situacao": "APTO", "partido": "PSB"}, {"cdCargo": 6, "cargo": "DEPUTADO FEDERAL", "id": 10001622405, "numero": 1225, "nomeUrna": "RAYNER NERI", "situacao": "APTO", "partido": "PDT"}, {"cdCargo": 7, "cargo": "DEPUTADO ESTADUAL", "id": 10001623548, "numero": 44111, "nomeUrna": "AUGUSTO", "situacao": "APTO", "partido": "UNI\u00c3O"}, {"cdCargo": 6, "cargo": "DEPUTADO FEDERAL", "id": 10001612484, "numero": 4488, "nomeUrna": "DR EDUARDO VELLOSO", "situacao": "APTO", "partido": "UNI\u00c3O"}, {"cdCargo": 7, "cargo": "DEPUTADO ESTADUAL", "id": 10001650025, "numero": 19555, "nomeUrna": "L\u00c9O ARA\u00daJO", "situacao": "APTO", "partido": "PODE"}, {"cdCargo": 7, "cargo": "DEPUTADO ESTADUAL", "id": 10001650035, "numero": 19192, "nomeUrna": "SAVANA SANTIAGO", "situacao": "APTO", "partido": "PODE"}, {"cdCargo": 7, "cargo": "DEPUTADO ESTADUAL", "id": 10001606214, "numero": 90789, "nomeUrna": "GILSOMAR OLIVEIRA", "situacao": "APTO", "partido": "PROS"}, {"cdCargo": 7, "cargo": "DEPUTADO ESTADUAL", "id": 10001670855, "numero": 51555, "nomeUrna": "IZAUTE VAZ", "situacao": "APTO", "partido": "PATRIOTA"}, {"cdCargo": 6, "cargo": "DEPUTADO FEDERAL", "id": 10001655352, "numero": 3344, "nomeUrna": "ANTONIO DANTAS", "situacao": "APTO", "partido": "PMN"}, {"cdCargo": 7, "cargo": "DEPUTADO ESTADUAL", "id": 10001724885, "numero": 15005, "nomeUrna": "SAYNA AMORIM", "situacao": "APTO", "partido": "MDB"}, {"cdCargo": 7, "cargo": "DEPUTADO ESTADUAL", "id": 10001642312, "numero": 15700, "nomeUrna": "ANTONIO CHUMB\u00c3O", "situacao": "APTO", "partido": "MDB"}, {"cdCargo": 7, "cargo": "DEPUTADO ESTADUAL", "id": 10001643325, "numero": 40700, "nomeUrna": "L\u00c9IA", "situacao": "APTO", "partido": "PSB"}, {"cdCargo": 6, "cargo": "DEPUTADO FEDERAL", "id": 10001614243, "numero": 3663, "nomeUrna": "SARAIVA GAMA", "situacao": "APTO", "partido": "AGIR"}, {"cdCargo": 7, "cargo": "DEPUTADO ESTADUAL", "id": 10001595360, "numero": 50223, "nomeUrna": "RENATO LOPES", "situacao": "APTO", "partido": "PSOL"}, {"cdCargo": 7, "cargo": "DEPUTADO ESTADUAL", "id": 10001622776, "numero": 12345, "nomeUrna": "JOSU\u00c9 DOURADO", "situacao": "APTO", "partido": "PDT"}, {"cdCargo": 7, "cargo": "DEPUTADO ESTADUAL", "id": 10001635529, "numero": 10222, "nomeUrna": "DRA HELANE CHRISTINA", "situacao": "APTO", "partido": "REPUBLICANOS"}, {"cdCargo": 6, "cargo": "DEPUTADO FEDERAL", "id": 10001643701, "numero": 7733, "nomeUrna": "JESUS SILVA", "situacao": "APTO", "partido": "SOLIDARIEDADE"}, {"cdCargo": 6, "cargo": "DEPUTADO FEDERAL", "id": 10001614193, "numero": 4343, "nomeUrna": "CLAUDIO EZEQUIEL", "situacao": "APTO", "partido": "PV"}, {"cdCargo": 7, "cargo": "DEPUTADO ESTADUAL", "id": 10001606498, "numero": 36007, "nomeUrna": "N\u00c1UAS", "situacao": "APTO", "partido": "AGIR"}, {"cdCargo": 6, "cargo": "DEPUTADO FEDERAL", "id": 10001619996, "numero": 1044, "nomeUrna": "CORONEL EUDEMIR", "situacao": "APTO", "partido": "REPUBLICANOS"}, {"cdCargo": 7, "cargo": "DEPUTADO ESTADUAL", "id": 10001642328, "numero": 15300, "nomeUrna": "ITALO MESQUITA", "situacao": "APTO", "partido": "MDB"}, {"cdCargo": 7, "cargo": "DEPUTADO ESTADUAL", "id": 10001642326, "numero": 15010, "nomeUrna": "TANACA", "situacao": "APTO", "partido": "MDB"}, {"cdCargo": 6, "cargo": "DEPUTADO FEDERAL", "id": 10001619991, "numero": 1090, "nomeUrna": "SARGENTO PAZ", "situacao": "APTO", "partido": "REPUBLICANOS"}, {"cdCargo": 7, "cargo": "DEPUTADO ESTADUAL", "id": 10001606505, "numero": 36333, "nomeUrna": "JAQUELINE MEDEIROS", "situacao": "APTO", "partido": "AGIR"}, {"cdCargo": 6, "cargo": "DEPUTADO FEDERAL", "id": 10001670874, "numero": 5122, "nomeUrna": "PASTOR RENILDO", "situacao": "APTO", "partido": "PATRIOTA"}, {"cdCargo": 7, "cargo": "DEPUTADO ESTADUAL", "id": 10001622765, "numero": 12300, "nomeUrna": "ADERL\u00c2NDIO FRAN\u00c7A", "situacao": "APTO", "partido": "PDT"}, {"cdCargo": 7, "cargo": "DEPUTADO ESTADUAL", "id": 10001655356, "numero": 33242, "nomeUrna": "PR ANTONIO ALMEIDA", "situacao": "APTO", "partido": "PMN"}, {"cdCargo": 7, "cargo": "DEPUTADO ESTADUAL", "id": 10001606504, "numero": 36116, "nomeUrna": "F\u00c1BIO DA JUDIA", "situacao": "APTO", "partido": "AGIR"}, {"cdCargo": 7, "cargo": "DEPUTADO ESTADUAL", "id": 10001649316, "numero": 22555, "nomeUrna": "ZENIL", "situacao": "APTO", "partido": "PL"}, {"cdCargo": 7, "cargo": "DEPUTADO ESTADUAL", "id": 10001724919, "numero": 15023, "nomeUrna": "LUCIMAR BRINDES", "situacao": "APTO", "partido": "MDB"}, {"cdCargo": 6, "cargo": "DEPUTADO FEDERAL", "id": 10001655717, "numero": 1991, "nomeUrna": "ISRAEL AQUILA", "situacao": "APTO", "partido": "PODE"}, {"cdCargo": 6, "cargo": "DEPUTADO FEDERAL", "id": 10001649412, "numero": 4004, "nomeUrna": "RIZO ARA\u00daJO", "situacao": "APTO", "partido": "PSB"}, {"cdCargo": 7, "cargo": "DEPUTADO ESTADUAL", "id": 10001635776, "numero": 65234, "nomeUrna": "LET\u00cdCIA", "situacao": "APTO", "partido": "PC do B"}, {"cdCargo": 7, "cargo": "DEPUTADO ESTADUAL", "id": 10001601438, "numero": 55223, "nomeUrna": "J\u00d4 CONSELHEIRA", "situacao": "APTO", "partido": "PSD"}, {"cdCargo": 6, "cargo": "DEPUTADO FEDERAL", "id": 10001606129, "numero": 9033, "nomeUrna": "ROG\u00c9RIO BARROS", "situacao": "APTO", "partido": "PROS"}, {"cdCargo": 6, "cargo": "DEPUTADO FEDERAL", "id": 10001716341, "numero": 4545, "nomeUrna": "S\u00c9RGIO BARROS", "situacao": "APTO", "partido": "PSDB"}, {"cdCargo": 7, "cargo": "DEPUTADO ESTADUAL", "id": 10001601435, "numero": 55456, "nomeUrna": "Z\u00c9 AUGUSTO", "situacao": "APTO", "partido": "PSD"}, {"cdCargo": 6, "cargo": "DEPUTADO FEDERAL", "id": 10001655725, "numero": 1999, "nomeUrna": "BRUNO MORAES", "situacao": "APTO", "partido": "PODE"}, {"cdCargo": 7, "cargo": "DEPUTADO ESTADUAL", "id": 10001606506, "numero": 36000, "nomeUrna": "ROBERTO PINTO", "situacao": "APTO", "partido": "AGIR"}, {"cdCargo": 7, "cargo": "DEPUTADO ESTADUAL", "id": 10001642321, "numero": 15015, "nomeUrna": "FRANCISCA BAS\u00cdLIO", "situacao": "APTO", "partido": "MDB"}, {"cdCargo": 7, "cargo": "DEPUTADO ESTADUAL", "id": 10001643844, "numero": 77200, "nomeUrna": "MANELZINHO", "situacao": "APTO", "partido": "SOLIDARIEDADE"}, {"cdCargo": 7, "cargo": "DEPUTADO ESTADUAL", "id": 10001643434, "numero": 11190, "nomeUrna": "DEINIFRANCE", "situacao": "APTO", "partido": "PP"}, {"cdCargo": 6, "cargo": "DEPUTADO FEDERAL", "id": 10001670872, "numero": 5133, "nomeUrna": "DYAN \u00c9 O MANOEL DO CARMO", "situacao": "APTO", "partido": "PATRIOTA"}, {"cdCargo": 7, "cargo": "DEPUTADO ESTADUAL", "id": 10001717437, "numero": 27222, "nomeUrna": "RAY", "situacao": "APTO", "partido": "DC"}, {"cdCargo": 7, "cargo": "DEPUTADO ESTADUAL", "id": 10001600524, "numero": 50333, "nomeUrna": "DINA", "situacao": "APTO", "partido": "PSOL"}, {"cdCargo": 7, "cargo": "DEPUTADO ESTADUAL", "id": 10001601436, "numero": 55422, "nomeUrna": "PAULO XIMENES", "situacao": "APTO", "partido": "PSD"}, {"cdCargo": 6, "cargo": "DEPUTADO FEDERAL", "id": 10001614197, "numero": 6513, "nomeUrna": "PERPETUA ALMEIDA", "situacao": "APTO", "partido": "PC do B"}, {"cdCargo": 7, "cargo": "DEPUTADO ESTADUAL", "id": 10001606202, "numero": 90777, "nomeUrna": "IRM\u00c3 CHAGUINHA", "situacao": "APTO", "partido": "PROS"}, {"cdCargo": 6, "cargo": "DEPUTADO FEDERAL", "id": 10001614194, "numero": 4333, "nomeUrna": "PROTETORA MAURA AKINO", "situacao": "APTO", "partido": "PV"}, {"cdCargo": 7, "cargo": "DEPUTADO ESTADUAL", "id": 10001606499, "numero": 36198, "nomeUrna": "ROMEU ENTREGADOR", "situacao": "APTO", "partido": "AGIR"}, {"cdCargo": 7, "cargo": "DEPUTADO ESTADUAL", "id": 10001643858, "numero": 77468, "nomeUrna": "PROFESSOR EDILEUDO", "situacao": "APTO", "partido": "SOLIDARIEDADE"}, {"cdCargo": 7, "cargo": "DEPUTADO ESTADUAL", "id": 10001670861, "numero": 51222, "nomeUrna": "PROF VALTEMIR EVANGELISTA", "situacao": "APTO", "partido": "PATRIOTA"}, {"cdCargo": 7, "cargo": "DEPUTADO ESTADUAL", "id": 10001595355, "numero": 50555, "nomeUrna": "DENNYS", "situacao": "APTO", "partido": "PSOL"}, {"cdCargo": 4, "cargo": "VICE-GOVERNADOR", "id": 10001623439, "numero": 44, "nomeUrna": "DRA GEORGIA MICHELETTI", "situacao": "APTO", "partido": "UNI\u00c3O"}, {"cdCargo": 7, "cargo": "DEPUTADO ESTADUAL", "id": 10001635779, "numero": 13111, "nomeUrna": "MAURO DEFESON", "situacao": "APTO", "partido": "PT"}, {"cdCargo": 10, "cargo": "2\u00ba SUPLENTE", "id": 10001643705, "numero": 222, "nomeUrna": "IVO GALV\u00c3O", "situacao": "APTO", "partido": "MDB"}, {"cdCargo": 7, "cargo": "DEPUTADO ESTADUAL", "id": 10001635541, "numero": 10000, "nomeUrna": "JAMYL ASFURY", "situacao": "APTO", "partido": "REPUBLICANOS"}, {"cdCargo": 7, "cargo": "DEPUTADO ESTADUAL", "id": 10001643843, "numero": 77234, "nomeUrna": "MARCIA LIMA", "situacao": "APTO", "partido": "SOLIDARIEDADE"}, {"cdCargo": 7, "cargo": "DEPUTADO ESTADUAL", "id": 10001601434, "numero": 55000, "nomeUrna": "HEITOR JUNIOR", "situacao": "APTO", "partido": "PSD"}, {"cdCargo": 7, "cargo": "DEPUTADO ESTADUAL", "id": 10001635533, "numero": 10444, "nomeUrna": "SUZANA LOBEU", "situacao": "APTO", "partido": "REPUBLICANOS"}, {"cdCargo": 7, "cargo": "DEPUTADO ESTADUAL", "id": 10001606220, "numero": 90800, "nomeUrna": "FRANCISCA SANTIAGO", "situacao": "APTO", "partido": "PROS"}, {"cdCargo": 7, "cargo": "DEPUTADO ESTADUAL", "id": 10001723804, "numero": 45045, "nomeUrna": "EVA GALV\u00c3O", "situacao": "APTO", "partido": "PSDB"}, {"cdCargo": 6, "cargo": "DEPUTADO FEDERAL", "id": 10001621645, "numero": 1106, "nomeUrna": "SAMIR BESTENE", "situacao": "APTO", "partido": "PP"}, {"cdCargo": 7, "cargo": "DEPUTADO ESTADUAL", "id": 10001649307, "numero": 22456, "nomeUrna": "OS\u00c9IAS SILVA", "situacao": "APTO", "partido": "PL"}, {"cdCargo": 7, "cargo": "DEPUTADO ESTADUAL", "id": 10001642322, "numero": 15444, "nomeUrna": "ADRIANA MAIA", "situacao": "APTO", "partido": "MDB"}, {"cdCargo": 6, "cargo": "DEPUTADO FEDERAL", "id": 10001612491, "numero": 4477, "nomeUrna": "MIRLA MIRANDA", "situacao": "APTO", "partido": "UNI\u00c3O"}, {"cdCargo": 7, "cargo": "DEPUTADO ESTADUAL", "id": 10001649318, "numero": 22444, "nomeUrna": "PASTOR ELISEU MOREIRA", "situacao": "APTO", "partido": "PL"}, {"cdCargo": 7, "cargo": "DEPUTADO ESTADUAL", "id": 10001622760, "numero": 12212, "nomeUrna": "GIGI", "situacao": "APTO", "partido": "PDT"}, {"cdCargo": 7, "cargo": "DEPUTADO ESTADUAL", "id": 10001670863, "numero": 51200, "nomeUrna": "JURACY NOGUEIRA", "situacao": "APTO", "partido": "PATRIOTA"}, {"cdCargo": 6, "cargo": "DEPUTADO FEDERAL", "id": 10001614248, "numero": 3628, "nomeUrna": "SORAIA RAMALHO", "situacao": "APTO", "partido": "AGIR"}, {"cdCargo": 7, "cargo": "DEPUTADO ESTADUAL", "id": 10001717436, "numero": 27123, "nomeUrna": "OSVALDO DO QUINTAL", "situacao": "APTO", "partido": "DC"}, {"cdCargo": 7, "cargo": "DEPUTADO ESTADUAL", "id": 10001643438, "numero": 11332, "nomeUrna": "JO\u00c3O CARLOS", "situacao": "APTO", "partido": "PP"}, {"cdCargo": 6, "cargo": "DEPUTADO FEDERAL", "id": 10001643703, "numero": 7788, "nomeUrna": "EDI CELULAR", "situacao": "APTO", "partido": "SOLIDARIEDADE"}, {"cdCargo": 7, "cargo": "DEPUTADO ESTADUAL", "id": 10001655359, "numero": 33123, "nomeUrna": "NAZAR\u00c9 DO TACAC\u00c1", "situacao": "APTO", "partido": "PMN"}, {"cdCargo": 7, "cargo": "DEPUTADO ESTADUAL", "id": 10001623535, "numero": 44234, "nomeUrna": "JANAINA DANTAS", "situacao": "APTO", "partido": "UNI\u00c3O"}, {"cdCargo": 7, "cargo": "DEPUTADO ESTADUAL", "id": 10001649322, "numero": 22888, "nomeUrna": "FRANCIRLEY BARROSO", "situacao": "APTO", "partido": "PL"}, {"cdCargo": 7, "cargo": "DEPUTADO ESTADUAL", "id": 10001601439, "numero": 55222, "nomeUrna": "YAEL SARAIVA", "situacao": "APTO", "partido": "PSD"}, {"cdCargo": 7, "cargo": "DEPUTADO ESTADUAL", "id": 10001606495, "numero": 36300, "nomeUrna": "DECA PINHEIRO", "situacao": "APTO", "partido": "AGIR"}, {"cdCargo": 4, "cargo": "VICE-GOVERNADOR", "id": 10001612477, "numero": 11, "nomeUrna": "MAILZA", "situacao": "APTO", "partido": "PP"}, {"cdCargo": 7, "cargo": "DEPUTADO ESTADUAL", "id": 10001623543, "numero": 44144, "nomeUrna": "EROS ASFURY", "situacao": "APTO", "partido": "UNI\u00c3O"}, {"cdCargo": 7, "cargo": "DEPUTADO ESTADUAL", "id": 10001723796, "numero": 45005, "nomeUrna": "TOINHO DO POVO", "situacao": "APTO", "partido": "PSDB"}, {"cdCargo": 7, "cargo": "DEPUTADO ESTADUAL", "id": 10001670853, "numero": 51333, "nomeUrna": "DEUSIMAR ALBUQUERQUE", "situacao": "APTO", "partido": "PATRIOTA"}, {"cdCargo": 6, "cargo": "DEPUTADO FEDERAL", "id": 10001642339, "numero": 1500, "nomeUrna": "MAJOR ROCHA", "situacao": "APTO", "partido": "MDB"}, {"cdCargo": 6, "cargo": "DEPUTADO FEDERAL", "id": 10001614246, "numero": 3636, "nomeUrna": "JINKINGS", "situacao": "APTO", "partido": "AGIR"}, {"cdCargo": 6, "cargo": "DEPUTADO FEDERAL", "id": 10001595346, "numero": 5022, "nomeUrna": "CRISTINA CARUTA", "situacao": "APTO", "partido": "PSOL"}, {"cdCargo": 7, "cargo": "DEPUTADO ESTADUAL", "id": 10001643440, "numero": 11234, "nomeUrna": "MANOEL MORAES", "situacao": "APTO", "partido": "PP"}, {"cdCargo": 7, "cargo": "DEPUTADO ESTADUAL", "id": 10001623537, "numero": 44777, "nomeUrna": "MARCIA ABREU", "situacao": "APTO", "partido": "UNI\u00c3O"}, {"cdCargo": 7, "cargo": "DEPUTADO ESTADUAL", "id": 10001670865, "numero": 51999, "nomeUrna": "MARIA ANT\u00d4NIA PROTETORA", "situacao": "APTO", "partido": "PATRIOTA"}, {"cdCargo": 7, "cargo": "DEPUTADO ESTADUAL", "id": 10001643324, "numero": 40000, "nomeUrna": "GABRIEL SANTOS", "situacao": "APTO", "partido": "PSB"}, {"cdCargo": 6, "cargo": "DEPUTADO FEDERAL", "id": 10001601534, "numero": 5522, "nomeUrna": "JESUITA ARRUDA", "situacao": "APTO", "partido": "PSD"}, {"cdCargo": 7, "cargo": "DEPUTADO ESTADUAL", "id": 10001649320, "numero": 22100, "nomeUrna": "PROFESSOR CLEMILTON", "situacao": "APTO", "partido": "PL"}, {"cdCargo": 6, "cargo": "DEPUTADO FEDERAL", "id": 10001649417, "numero": 4088, "nomeUrna": "KELLY CRISTINA ", "situacao": "APTO", "partido": "PSB"}, {"cdCargo": 6, "cargo": "DEPUTADO FEDERAL", "id": 10001601539, "numero": 5500, "nomeUrna": "MOISES MEDEIROS", "situacao": "APTO", "partido": "PSD"}, {"cdCargo": 7, "cargo": "DEPUTADO ESTADUAL", "id": 10001606211, "numero": 90111, "nomeUrna": "DR. GILSON LEIT\u00c3O", "situacao": "APTO", "partido": "PROS"}, {"cdCargo": 6, "cargo": "DEPUTADO FEDERAL", "id": 10001716345, "numero": 4515, "nomeUrna": "MARCIA MARIA", "situacao": "APTO", "partido": "PSDB"}, {"cdCargo": 7, "cargo": "DEPUTADO ESTADUAL", "id": 10001723786, "numero": 45000, "nomeUrna": "CLOVIS NUNES", "situacao": "APTO", "partido": "PSDB"}, {"cdCargo": 6, "cargo": "DEPUTADO FEDERAL", "id": 10001606131, "numero": 9099, "nomeUrna": "WILLINGTON (WA)", "situacao": "APTO", "partido": "PROS"}, {"cdCargo": 6, "cargo": "DEPUTADO FEDERAL", "id": 10001619992, "numero": 1022, "nomeUrna": "KEILIANE CORDEIRO", "situacao": "APTO", "partido": "REPUBLICANOS"}, {"cdCargo": 6, "cargo": "DEPUTADO FEDERAL", "id": 10001655722, "numero": 1911, "nomeUrna": "LEILA HOLANDA", "situacao": "APTO", "partido": "PODE"}, {"cdCargo": 7, "cargo": "DEPUTADO ESTADUAL", "id": 10001643427, "numero": 11133, "nomeUrna": "MARIA ANT\u00d4NIA", "situacao": "APTO", "partido": "PP"}, {"cdCargo": 3, "cargo": "GOVERNADOR", "id": 10001612476, "numero": 11, "nomeUrna": "GLADSON CAMELI", "situacao": "APTO", "partido": "PP"}, {"cdCargo": 7, "cargo": "DEPUTADO ESTADUAL", "id": 10001600523, "numero": 50000, "nomeUrna": "DUDA MARQUES", "situacao": "APTO", "partido": "PSOL"}, {"cdCargo": 7, "cargo": "DEPUTADO ESTADUAL", "id": 10001601427, "numero": 55777, "nomeUrna": "PABLO BREGENSE", "situacao": "APTO", "partido": "PSD"}, {"cdCargo": 9, "cargo": "1\u00ba SUPLENTE", "id": 10001643707, "numero": 222, "nomeUrna": "BETH PINHEIRO", "situacao": "APTO", "partido": "PL"}, {"cdCargo": 7, "cargo": "DEPUTADO ESTADUAL", "id": 10001635767, "numero": 13613, "nomeUrna": "ADONAY", "situacao": "APTO", "partido": "PT"}, {"cdCargo": 9, "cargo": "1\u00ba SUPLENTE", "id": 10001731818, "numero": 199, "nomeUrna": "LURDINHA LIMA", "situacao": "APTO", "partido": "PP"}, {"cdCargo": 6, "cargo": "DEPUTADO FEDERAL", "id": 10001601532, "numero": 5555, "nomeUrna": "LENE PETEC\u00c3O", "situacao": "APTO", "partido": "PSD"}, {"cdCargo": 7, "cargo": "DEPUTADO ESTADUAL", "id": 10001642317, "numero": 15321, "nomeUrna": "LOURIVAL MARQUES", "situacao": "APTO", "partido": "MDB"}, {"cdCargo": 7, "cargo": "DEPUTADO ESTADUAL", "id": 10001643855, "numero": 77789, "nomeUrna": "MOIS\u00c9S DINIZ ", "situacao": "APTO", "partido": "SOLIDARIEDADE"}, {"cdCargo": 7, "cargo": "DEPUTADO ESTADUAL", "id": 10001635770, "numero": 13777, "nomeUrna": "MARCELO MAC\u00caDO", "situacao": "APTO", "partido": "PT"}, {"cdCargo": 7, "cargo": "DEPUTADO ESTADUAL", "id": 10001642320, "numero": 15678, "nomeUrna": "LEILA GALV\u00c3O", "situacao": "APTO", "partido": "MDB"}, {"cdCargo": 7, "cargo": "DEPUTADO ESTADUAL", "id": 10001623538, "numero": 44004, "nomeUrna": "FRANCINEUDO COSTA", "situacao": "APTO", "partido": "UNI\u00c3O"}, {"cdCargo": 6, "cargo": "DEPUTADO FEDERAL", "id": 10001601537, "numero": 5511, "nomeUrna": "FRANCISCO PIY\u00c3KO", "situacao": "APTO", "partido": "PSD"}, {"cdCargo": 7, "cargo": "DEPUTADO ESTADUAL", "id": 10001670854, "numero": 51234, "nomeUrna": "PEPES", "situacao": "APTO", "partido": "PATRIOTA"}, {"cdCargo": 6, "cargo": "DEPUTADO FEDERAL", "id": 10001622413, "numero": 1223, "nomeUrna": "ADRIANA MELO", "situacao": "APTO", "partido": "PDT"}, {"cdCargo": 6, "cargo": "DEPUTADO FEDERAL", "id": 10001612490, "numero": 4401, "nomeUrna": "LUIZ ANUTE", "situacao": "APTO", "partido": "UNI\u00c3O"}, {"cdCargo": 6, "cargo": "DEPUTADO FEDERAL", "id": 10001622408, "numero": 1212, "nomeUrna": "JESUS S\u00c9RGIO", "situacao": "APTO", "partido": "PDT"}, {"cdCargo": 7, "cargo": "DEPUTADO ESTADUAL", "id": 10001723790, "numero": 23456, "nomeUrna": "MAURICIO DOS ESPETINHOS", "situacao": "APTO", "partido": "CIDADANIA"}, {"cdCargo": 7, "cargo": "DEPUTADO ESTADUAL", "id": 10001649314, "numero": 22300, "nomeUrna": "CORONEL AUGUSTO MACIEL", "situacao": "APTO", "partido": "PL"}, {"cdCargo": 7, "cargo": "DEPUTADO ESTADUAL", "id": 10001635532, "numero": 10022, "nomeUrna": "PEDRO DO DAYANE", "situacao": "APTO", "partido": "REPUBLICANOS"}, {"cdCargo": 7, "cargo": "DEPUTADO ESTADUAL", "id": 10001635537, "numero": 10555, "nomeUrna": "CLODOALDO RODRIGUES", "situacao": "APTO", "partido": "REPUBLICANOS"}, {"cdCargo": 7, "cargo": "DEPUTADO ESTADUAL", "id": 10001642310, "numero": 15234, "nomeUrna": "NESIO CARVALHO", "situacao": "APTO", "partido": "MDB"}, {"cdCargo": 7, "cargo": "DEPUTADO ESTADUAL", "id": 10001642319, "numero": 15122, "nomeUrna": "ANTONIA SALES", "situacao": "APTO", "partido": "MDB"}, {"cdCargo": 6, "cargo": "DEPUTADO FEDERAL", "id": 10001613552, "numero": 6565, "nomeUrna": "Z\u00c9 DA ROSA", "situacao": "APTO", "partido": "PC do B"}, {"cdCargo": 7, "cargo": "DEPUTADO ESTADUAL", "id": 10001649323, "numero": 22123, "nomeUrna": "YARGO RODRIGUES", "situacao": "APTO", "partido": "PL"}, {"cdCargo": 6, "cargo": "DEPUTADO FEDERAL", "id": 10001606134, "numero": 9009, "nomeUrna": "ANA PAULA", "situacao": "APTO", "partido": "PROS"}, {"cdCargo": 7, "cargo": "DEPUTADO ESTADUAL", "id": 10001642327, "numero": 15000, "nomeUrna": "EMERSON JARUDE", "situacao": "APTO", "partido": "MDB"}, {"cdCargo": 6, "cargo": "DEPUTADO FEDERAL", "id": 10001642336, "numero": 1507, "nomeUrna": "ALDA RADINE", "situacao": "APTO", "partido": "MDB"}, {"cdCargo": 6, "cargo": "DEPUTADO FEDERAL", "id": 10001643700, "numero": 7789, "nomeUrna": "JANES PETECA", "situacao": "APTO", "partido": "SOLIDARIEDADE"}, {"cdCargo": 7, "cargo": "DEPUTADO ESTADUAL", "id": 10001723795, "numero": 45011, "nomeUrna": "DAIANE SILVA", "situacao": "APTO", "partido": "PSDB"}, {"cdCargo": 7, "cargo": "DEPUTADO ESTADUAL", "id": 10001635769, "numero": 13456, "nomeUrna": "JUNIOR MANCHINERI", "situacao": "APTO", "partido": "PT"}, {"cdCargo": 6, "cargo": "DEPUTADO FEDERAL", "id": 10001642332, "numero": 1555, "nomeUrna": "FLAVIANO MELO", "situacao": "APTO", "partido": "MDB"}, {"cdCargo": 7, "cargo": "DEPUTADO ESTADUAL", "id": 10001670867, "numero": 51100, "nomeUrna": "SERGIO RODRIGUES", "situacao": "APTO", "partido": "PATRIOTA"}, {"cdCargo": 9, "cargo": "1\u00ba SUPLENTE", "id": 10001606584, "numero": 364, "nomeUrna": "TIAGO FARIAS", "situacao": "APTO", "partido": "AGIR"}, {"cdCargo": 7, "cargo": "DEPUTADO ESTADUAL", "id": 10001623540, "numero": 44044, "nomeUrna": "SOCORRO AMORIM", "situacao": "APTO", "partido": "UNI\u00c3O"}, {"cdCargo": 7, "cargo": "DEPUTADO ESTADUAL", "id": 10001623552, "numero": 44555, "nomeUrna": "WHENDY LIMA", "situacao": "APTO", "partido": "UNI\u00c3O"}, {"cdCargo": 7, "cargo": "DEPUTADO ESTADUAL", "id": 10001643846, "numero": 77890, "nomeUrna": "MISSION\u00c1RIA KATIA", "situacao": "APTO", "partido": "SOLIDARIEDADE"}, {"cdCargo": 5, "cargo": "SENADOR", "id": 10001601615, "numero": 900, "nomeUrna": "DRA. VANDA MILANI", "situacao": "APTO", "partido": "PROS"}, {"cdCargo": 7, "cargo": "DEPUTADO ESTADUAL", "id": 10001649311, "numero": 22111, "nomeUrna": "JUCY", "situacao": "APTO", "partido": "PL"}, {"cdCargo": 7, "cargo": "DEPUTADO ESTADUAL", "id": 10001649313, "numero": 22000, "nomeUrna": "TEREZINHA MOREIRA", "situacao": "APTO", "partido": "PL"}, {"cdCargo": 6, "cargo": "DEPUTADO FEDERAL", "id": 10001622409, "numero": 1227, "nomeUrna": "EMIR MENDON\u00c7A", "situacao": "APTO", "partido": "PDT"}, {"cdCargo": 10, "cargo": "2\u00ba SUPLENTE", "id": 10001643546, "numero": 131, "nomeUrna": "TI\u00c3O BRUZUGU", "situacao": "APTO", "partido": "PV"}, {"cdCargo": 6, "cargo": "DEPUTADO FEDERAL", "id": 10001670873, "numero": 5115, "nomeUrna": "NAZARE PEIXOTO", "situacao": "APTO", "partido": "PATRIOTA"}, {"cdCargo": 7, "cargo": "DEPUTADO ESTADUAL", "id": 10001622781, "numero": 12000, "nomeUrna": "JOS\u00c9 MASTRANGELO", "situacao": "APTO", "partido": "PDT"}, {"cdCargo": 7, "cargo": "DEPUTADO ESTADUAL", "id": 10001595350, "numero": 50099, "nomeUrna": "YASMIN GRANGEIRO", "situacao": "APTO", "partido": "PSOL"}, {"cdCargo": 7, "cargo": "DEPUTADO ESTADUAL", "id": 10001622767, "numero": 12133, "nomeUrna": "JOAQUIM FLOR\u00caNCIO", "situacao": "APTO", "partido": "PDT"}, {"cdCargo": 7, "cargo": "DEPUTADO ESTADUAL", "id": 10001601437, "numero": 55100, "nomeUrna": "KASSIO ARA\u00daJO", "situacao": "APTO", "partido": "PSD"}, {"cdCargo": 7, "cargo": "DEPUTADO ESTADUAL", "id": 10001635772, "numero": 13122, "nomeUrna": "ROSALINA", "situacao": "APTO", "partido": "PT"}, {"cdCargo": 6, "cargo": "DEPUTADO FEDERAL", "id": 10001716343, "numero": 4522, "nomeUrna": "SGT LEORNE", "situacao": "APTO", "partido": "PSDB"}, {"cdCargo": 7, "cargo": "DEPUTADO ESTADUAL", "id": 10001601446, "numero": 55555, "nomeUrna": "DR M\u00c1RIO MARCELO", "situacao": "APTO", "partido": "PSD"}, {"cdCargo": 7, "cargo": "DEPUTADO ESTADUAL", "id": 10001642315, "numero": 15615, "nomeUrna": "CHICO DO ESPORTE", "situacao": "APTO", "partido": "MDB"}, {"cdCargo": 7, "cargo": "DEPUTADO ESTADUAL", "id": 10001650033, "numero": 19999, "nomeUrna": "FAGNER CALEG\u00c1RIO", "situacao": "APTO", "partido": "PODE"}, {"cdCargo": 5, "cargo": "SENADOR", "id": 10001643446, "numero": 400, "nomeUrna": "DR. JENILSON LEITE", "situacao": "APTO", "partido": "PSB"}, {"cdCargo": 7, "cargo": "DEPUTADO ESTADUAL", "id": 10001595357, "numero": 50510, "nomeUrna": "GILBERTO MEDEIROS", "situacao": "APTO", "partido": "PSOL"}, {"cdCargo": 7, "cargo": "DEPUTADO ESTADUAL", "id": 10001623544, "numero": 44999, "nomeUrna": "OTON SALES", "situacao": "APTO", "partido": "UNI\u00c3O"}, {"cdCargo": 7, "cargo": "DEPUTADO ESTADUAL", "id": 10001606200, "numero": 90123, "nomeUrna": "CORONEL BATISTA", "situacao": "APTO", "partido": "PROS"}, {"cdCargo": 7, "cargo": "DEPUTADO ESTADUAL", "id": 10001606206, "numero": 90321, "nomeUrna": "RAY SANTOS", "situacao": "APTO", "partido": "PROS"}, {"cdCargo": 6, "cargo": "DEPUTADO FEDERAL", "id": 10001614242, "numero": 3654, "nomeUrna": "EMILSON CHAVES", "situacao": "APTO", "partido": "AGIR"}, {"cdCargo": 7, "cargo": "DEPUTADO ESTADUAL", "id": 10001643848, "numero": 77122, "nomeUrna": "JOSSICLEUDO MELO", "situacao": "APTO", "partido": "SOLIDARIEDADE"}, {"cdCargo": 7, "cargo": "DEPUTADO ESTADUAL", "id": 10001635764, "numero": 13131, "nomeUrna": "JOCI AGUIAR", "situacao": "APTO", "partido": "PT"}, {"cdCargo": 6, "cargo": "DEPUTADO FEDERAL", "id": 10001621650, "numero": 1111, "nomeUrna": "GERLEN DINIZ", "situacao": "APTO", "partido": "PP"}, {"cdCargo": 6, "cargo": "DEPUTADO FEDERAL", "id": 10001606127, "numero": 9044, "nomeUrna": "EDNA NANTES", "situacao": "APTO", "partido": "PROS"}, {"cdCargo": 7, "cargo": "DEPUTADO ESTADUAL", "id": 10001606204, "numero": 90987, "nomeUrna": "ROSILDA SILVA", "situacao": "APTO", "partido": "PROS"}, {"cdCargo": 7, "cargo": "DEPUTADO ESTADUAL", "id": 10001649324, "numero": 22002, "nomeUrna": "EVA DANTAS", "situacao": "APTO", "partido": "PL"}, {"cdCargo": 9, "cargo": "1\u00ba SUPLENTE", "id": 10001643444, "numero": 400, "nomeUrna": "C\u00c9SAR MESSIAS", "situacao": "APTO", "partido": "PSB"}, {"cdCargo": 6, "cargo": "DEPUTADO FEDERAL", "id": 10001601533, "numero": 5588, "nomeUrna": "JUAREZ LEIT\u00c3O", "situacao": "APTO", "partido": "PSD"}, {"cdCargo": 4, "cargo": "VICE-GOVERNADOR", "id": 10001595335, "numero": 50, "nomeUrna": "JANE ROSAS", "situacao": "APTO", "partido": "PSOL"}, {"cdCargo": 7, "cargo": "DEPUTADO ESTADUAL", "id": 10001643431, "numero": 11321, "nomeUrna": "SANTIAGO", "situacao": "APTO", "partido": "PP"}, {"cdCargo": 7, "cargo": "DEPUTADO ESTADUAL", "id": 10001650031, "numero": 19000, "nomeUrna": "BETE MIRANDA", "situacao": "APTO", "partido": "PODE"}, {"cdCargo": 7, "cargo": "DEPUTADO ESTADUAL", "id": 10001622762, "numero": 12111, "nomeUrna": "MARCUS CAVALCANTE", "situacao": "APTO", "partido": "PDT"}, {"cdCargo": 7, "cargo": "DEPUTADO ESTADUAL", "id": 10001601432, "numero": 55678, "nomeUrna": "PROF MARQUINHO", "situacao": "APTO", "partido": "PSD"}, {"cdCargo": 7, "cargo": "DEPUTADO ESTADUAL", "id": 10001642329, "numero": 15333, "nomeUrna": "PROFESSOR LUAN LUZ", "situacao": "APTO", "partido": "MDB"}, {"cdCargo": 7, "cargo": "DEPUTADO ESTADUAL", "id": 10001606496, "numero": 36123, "nomeUrna": "DIR SILVA", "situacao": "APTO", "partido": "AGIR"}, {"cdCargo": 6, "cargo": "DEPUTADO FEDERAL", "id": 10001622412, "numero": 1277, "nomeUrna": "ORLEILSON CAMELI", "situacao": "APTO", "partido": "PDT"}, {"cdCargo": 6, "cargo": "DEPUTADO FEDERAL", "id": 10001601538, "numero": 5544, "nomeUrna": "GESSI CAPEL\u00c3O", "situacao": "APTO", "partido": "PSD"}, {"cdCargo": 10, "cargo": "2\u00ba SUPLENTE", "id": 10001601614, "numero": 900, "nomeUrna": "JOS\u00c9 COSTA", "situacao": "APTO", "partido": "PTB"}, {"cdCargo": 7, "cargo": "DEPUTADO ESTADUAL", "id": 10001642331, "numero": 15111, "nomeUrna": "ESPERIDI\u00c3O MENEZES JUNIOR", "situacao": "APTO", "partido": "MDB"}, {"cdCargo": 7, "cargo": "DEPUTADO ESTADUAL", "id": 10001635530, "numero": 10190, "nomeUrna": "SARGENTO MENDON\u00c7A", "situacao": "APTO", "partido": "REPUBLICANOS"}, {"cdCargo": 3, "cargo": "GOVERNADOR", "id": 10001639519, "numero": 15, "nomeUrna": "MARA ROCHA", "situacao": "APTO", "partido": "MDB"}, {"cdCargo": 7, "cargo": "DEPUTADO ESTADUAL", "id": 10001650026, "numero": 19789, "nomeUrna": "NIL CRISPIM", "situacao": "APTO", "partido": "PODE"}, {"cdCargo": 7, "cargo": "DEPUTADO ESTADUAL", "id": 10001622779, "numero": 12222, "nomeUrna": "TOM S\u00c9RGIO", "situacao": "APTO", "partido": "PDT"}, {"cdCargo": 7, "cargo": "DEPUTADO ESTADUAL", "id": 10001606205, "numero": 90222, "nomeUrna": "CHICARLOS", "situacao": "APTO", "partido": "PROS"}, {"cdCargo": 6, "cargo": "DEPUTADO FEDERAL", "id": 10001649410, "numero": 4055, "nomeUrna": "RUBBY RODRIGUES ", "situacao": "APTO", "partido": "PSB"}, {"cdCargo": 7, "cargo": "DEPUTADO ESTADUAL", "id": 10001601441, "numero": 55255, "nomeUrna": "F\u00c1TIMA MACIEL", "situacao": "APTO", "partido": "PSD"}, {"cdCargo": 6, "cargo": "DEPUTADO FEDERAL", "id": 10001612486, "numero": 4455, "nomeUrna": "MEIRE SERAFIM", "situacao": "APTO", "partido": "UNI\u00c3O"}, {"cdCargo": 6, "cargo": "DEPUTADO FEDERAL", "id": 10001670869, "numero": 5188, "nomeUrna": "PASTOR ANT\u00d4NIO JOS\u00c9", "situacao": "APTO", "partido": "PATRIOTA"}, {"cdCargo": 6, "cargo": "DEPUTADO FEDERAL", "id": 10001643702, "numero": 7777, "nomeUrna": "L\u00cdCIA FIDELIS", "situacao": "APTO", "partido": "SOLIDARIEDADE"}, {"cdCargo": 3, "cargo": "GOVERNADOR", "id": 10001606307, "numero": 36, "nomeUrna": "DAVID HALL", "situacao": "APTO", "partido": "AGIR"}, {"cdCargo": 6, "cargo": "DEPUTADO FEDERAL", "id": 10001622411, "numero": 1221, "nomeUrna": "DJE CAVALCANTE", "situacao": "APTO", "partido": "PDT"}, {"cdCargo": 6, "cargo": "DEPUTADO FEDERAL", "id": 10001655723, "numero": 1910, "nomeUrna": "LUDMILLA CAVALCANTE", "situacao": "APTO", "partido": "PODE"}, {"cdCargo": 7, "cargo": "DEPUTADO ESTADUAL", "id": 10001622764, "numero": 12190, "nomeUrna": "WALDERLAN LIMA", "situacao": "APTO", "partido": "PDT"}, {"cdCargo": 7, "cargo": "DEPUTADO ESTADUAL", "id": 10001606208, "numero": 90555, "nomeUrna": "POLICIAL ARA\u00daJO", "situacao": "APTO", "partido": "PROS"}, {"cdCargo": 7, "cargo": "DEPUTADO ESTADUAL", "id": 10001623533, "numero": 44444, "nomeUrna": "GILBERTO LIRA", "situacao": "APTO", "partido": "UNI\u00c3O"}, {"cdCargo": 7, "cargo": "DEPUTADO ESTADUAL", "id": 10001623541, "numero": 44789, "nomeUrna": "DECIO HUNIKUI", "situacao": "APTO", "partido": "UNI\u00c3O"}, {"cdCargo": 7, "cargo": "DEPUTADO ESTADUAL", "id": 10001649325, "numero": 22001, "nomeUrna": "LUCA DO RONALDO", "situacao": "APTO", "partido": "PL"}, {"cdCargo": 7, "cargo": "DEPUTADO ESTADUAL", "id": 10001643436, "numero": 11777, "nomeUrna": "BRANCA DO LIBERDADE", "situacao": "APTO", "partido": "PP"}, {"cdCargo": 7, "cargo": "DEPUTADO ESTADUAL", "id": 10001601443, "numero": 55111, "nomeUrna": "PASTORA CLEI\u00c7A FRAN\u00c7A", "situacao": "APTO", "partido": "PSD"}, {"cdCargo": 7, "cargo": "DEPUTADO ESTADUAL", "id": 10001670864, "numero": 51444, "nomeUrna": "LEONCIO CASTRO", "situacao": "APTO", "partido": "PATRIOTA"}, {"cdCargo": 6, "cargo": "DEPUTADO FEDERAL", "id": 10001595342, "numero": 5055, "nomeUrna": "NILDA SAUL", "situacao": "APTO", "partido": "PSOL"}, {"cdCargo": 7, "cargo": "DEPUTADO ESTADUAL", "id": 10001643847, "numero": 77321, "nomeUrna": "LITA ARA\u00daJO", "situacao": "APTO", "partido": "SOLIDARIEDADE"}, {"cdCargo": 7, "cargo": "DEPUTADO ESTADUAL", "id": 10001723791, "numero": 45555, "nomeUrna": "SOCORRO MARTINS", "situacao": "APTO", "partido": "PSDB"}, {"cdCargo": 7, "cargo": "DEPUTADO ESTADUAL", "id": 10001642316, "numero": 15222, "nomeUrna": "JUNIOR MOREIRA", "situacao": "APTO", "partido": "MDB"}, {"cdCargo": 7, "cargo": "DEPUTADO ESTADUAL", "id": 10001724920, "numero": 15611, "nomeUrna": "DANIEL DORZILA", "situacao": "APTO", "partido": "MDB"}, {"cdCargo": 6, "cargo": "DEPUTADO FEDERAL", "id": 10001619990, "numero": 1000, "nomeUrna": "ANT\u00d4NIA LUCIA", "situacao": "APTO", "partido": "REPUBLICANOS"}, {"cdCargo": 7, "cargo": "DEPUTADO ESTADUAL", "id": 10001595356, "numero": 50500, "nomeUrna": "WALDIR FRAN\u00c7A", "situacao": "APTO", "partido": "PSOL"}, {"cdCargo": 7, "cargo": "DEPUTADO ESTADUAL", "id": 10001739225, "numero": 23111, "nomeUrna": "NEDELY SOUSA", "situacao": "APTO", "partido": "CIDADANIA"}, {"cdCargo": 7, "cargo": "DEPUTADO ESTADUAL", "id": 10001643439, "numero": 11106, "nomeUrna": "BESTENE", "situacao": "APTO", "partido": "PP"}, {"cdCargo": 7, "cargo": "DEPUTADO ESTADUAL", "id": 10001601429, "numero": 55012, "nomeUrna": "RUBENS RODRIGUES", "situacao": "APTO", "partido": "PSD"}, {"cdCargo": 7, "cargo": "DEPUTADO ESTADUAL", "id": 10001606199, "numero": 90680, "nomeUrna": "ADEVILSON QUEIROZ", "situacao": "APTO", "partido": "PROS"}, {"cdCargo": 6, "cargo": "DEPUTADO FEDERAL", "id": 10001642337, "numero": 1512, "nomeUrna": "AMARALDO PASCOAL", "situacao": "APTO", "partido": "MDB"}, {"cdCargo": 7, "cargo": "DEPUTADO ESTADUAL", "id": 10001606218, "numero": 90444, "nomeUrna": "BRIGIDO OLIVEIRA", "situacao": "APTO", "partido": "PROS"}, {"cdCargo": 6, "cargo": "DEPUTADO FEDERAL", "id": 10001649416, "numero": 4000, "nomeUrna": "EVANDRO ROSAS BAR\u00c3O", "situacao": "APTO", "partido": "PSB"}, {"cdCargo": 6, "cargo": "DEPUTADO FEDERAL", "id": 10001642334, "numero": 1567, "nomeUrna": "RAPHAEL BASTOS", "situacao": "APTO", "partido": "MDB"}, {"cdCargo": 7, "cargo": "DEPUTADO ESTADUAL", "id": 10001717432, "numero": 27888, "nomeUrna": "JOANNA AYSHA", "situacao": "APTO", "partido": "DC"}, {"cdCargo": 7, "cargo": "DEPUTADO ESTADUAL", "id": 10001595351, "numero": 50777, "nomeUrna": "CHICO DO ODER", "situacao": "APTO", "partido": "PSOL"}, {"cdCargo": 7, "cargo": "DEPUTADO ESTADUAL", "id": 10001643433, "numero": 11888, "nomeUrna": "ARLETE AMARAL", "situacao": "APTO", "partido": "PP"}, {"cdCargo": 7, "cargo": "DEPUTADO ESTADUAL", "id": 10001649326, "numero": 22333, "nomeUrna": "ARLENILSON CUNHA", "situacao": "APTO", "partido": "PL"}, {"cdCargo": 7, "cargo": "DEPUTADO ESTADUAL", "id": 10001723787, "numero": 45007, "nomeUrna": "CICERO FURTADO", "situacao": "APTO", "partido": "PSDB"}, {"cdCargo": 10, "cargo": "2\u00ba SUPLENTE", "id": 10001714549, "numero": 444, "nomeUrna": "CORONEL CASAGRANDE", "situacao": "APTO", "partido": "UNI\u00c3O"}, {"cdCargo": 6, "cargo": "DEPUTADO FEDERAL", "id": 10001643697, "numero": 7799, "nomeUrna": "MAURICIO DINIZ", "situacao": "APTO", "partido": "SOLIDARIEDADE"}, {"cdCargo": 7, "cargo": "DEPUTADO ESTADUAL", "id": 10001643432, "numero": 11123, "nomeUrna": "BEBE BOLSONARO", "situacao": "APTO", "partido": "PP"}, {"cdCargo": 7, "cargo": "DEPUTADO ESTADUAL", "id": 10001606497, "numero": 36036, "nomeUrna": "MANOEL DA BAIXADA", "situacao": "APTO", "partido": "AGIR"}, {"cdCargo": 6, "cargo": "DEPUTADO FEDERAL", "id": 10001643698, "numero": 7727, "nomeUrna": "ANDERSON LIMA", "situacao": "APTO", "partido": "SOLIDARIEDADE"}, {"cdCargo": 7, "cargo": "DEPUTADO ESTADUAL", "id": 10001650029, "numero": 19777, "nomeUrna": "BRUNO SANTOS", "situacao": "APTO", "partido": "PODE"}, {"cdCargo": 7, "cargo": "DEPUTADO ESTADUAL", "id": 10001635535, "numero": 10123, "nomeUrna": "TIA KATIANE", "situacao": "APTO", "partido": "REPUBLICANOS"}, {"cdCargo": 5, "cargo": "SENADOR", "id": 10001595339, "numero": 500, "nomeUrna": "SANDERSON MOURA", "situacao": "APTO", "partido": "PSOL"}, {"cdCargo": 7, "cargo": "DEPUTADO ESTADUAL", "id": 10001601442, "numero": 55655, "nomeUrna": "MIRTES SOUZA", "situacao": "APTO", "partido": "PSD"}, {"cdCargo": 7, "cargo": "DEPUTADO ESTADUAL", "id": 10001643849, "numero": 77252, "nomeUrna": "AFONSO CONTADOR", "situacao": "APTO", "partido": "SOLIDARIEDADE"}, {"cdCargo": 7, "cargo": "DEPUTADO ESTADUAL", "id": 10001643860, "numero": 77889, "nomeUrna": "PAULO ARA\u00daJO", "situacao": "APTO", "partido": "SOLIDARIEDADE"}, {"cdCargo": 7, "cargo": "DEPUTADO ESTADUAL", "id": 10001730227, "numero": 51008, "nomeUrna": "MARIA APARECIDA LIMA", "situacao": "APTO", "partido": "PATRIOTA"}, {"cdCargo": 7, "cargo": "DEPUTADO ESTADUAL", "id": 10001643845, "numero": 77121, "nomeUrna": "MARCELO BRILHANTE", "situacao": "APTO", "partido": "SOLIDARIEDADE"}, {"cdCargo": 6, "cargo": "DEPUTADO FEDERAL", "id": 10001670871, "numero": 5151, "nomeUrna": "JH", "situacao": "APTO", "partido": "PATRIOTA"}, {"cdCargo": 7, "cargo": "DEPUTADO ESTADUAL", "id": 10001623550, "numero": 44000, "nomeUrna": "HELENA SILVA", "situacao": "APTO", "partido": "UNI\u00c3O"}, {"cdCargo": 7, "cargo": "DEPUTADO ESTADUAL", "id": 10001643443, "numero": 11111, "nomeUrna": "SANDRO TREME CAR", "situacao": "APTO", "partido": "PP"}, {"cdCargo": 7, "cargo": "DEPUTADO ESTADUAL", "id": 10001635536, "numero": 10345, "nomeUrna": "EBER MACHADO", "situacao": "APTO", "partido": "REPUBLICANOS"}, {"cdCargo": 7, "cargo": "DEPUTADO ESTADUAL", "id": 10001643323, "numero": 40400, "nomeUrna": "GELMIRES LIMA", "situacao": "APTO", "partido": "PSB"}, {"cdCargo": 5, "cargo": "SENADOR", "id": 10001649256, "numero": 199, "nomeUrna": "NEY AMORIM", "situacao": "APTO", "partido": "PODE"}, {"cdCargo": 7, "cargo": "DEPUTADO ESTADUAL", "id": 10001650034, "numero": 19456, "nomeUrna": "PASTOR ARNALDO BARROS", "situacao": "APTO", "partido": "PODE"}, {"cdCargo": 6, "cargo": "DEPUTADO FEDERAL", "id": 10001606130, "numero": 9090, "nomeUrna": "ROBERTO DA PRINCEZINHA", "situacao": "APTO", "partido": "PROS"}, {"cdCargo": 7, "cargo": "DEPUTADO ESTADUAL", "id": 10001670859, "numero": 51190, "nomeUrna": "DELEGADO ROBERTH ALENCAR", "situacao": "APTO", "partido": "PATRIOTA"}, {"cdCargo": 6, "cargo": "DEPUTADO FEDERAL", "id": 10001649413, "numero": 4044, "nomeUrna": "L\u00daBIA ARA\u00daJO", "situacao": "APTO", "partido": "PSB"}, {"cdCargo": 6, "cargo": "DEPUTADO FEDERAL", "id": 10001622406, "numero": 1200, "nomeUrna": "R\u00d4 DA BASE", "situacao": "APTO", "partido": "PDT"}, {"cdCargo": 6, "cargo": "DEPUTADO FEDERAL", "id": 10001622410, "numero": 1234, "nomeUrna": "JORGE LU\u00cdS", "situacao": "APTO", "partido": "PDT"}, {"cdCargo": 7, "cargo": "DEPUTADO ESTADUAL", "id": 10001601425, "numero": 55444, "nomeUrna": "DRIELLE MENDES", "situacao": "APTO", "partido": "PSD"}, {"cdCargo": 7, "cargo": "DEPUTADO ESTADUAL", "id": 10001635762, "numero": 43123, "nomeUrna": "ITAMARA SOUZA", "situacao": "APTO", "partido": "PV"}, {"cdCargo": 6, "cargo": "DEPUTADO FEDERAL", "id": 10001716348, "numero": 2345, "nomeUrna": "CARLOS LEANDRO", "situacao": "APTO", "partido": "CIDADANIA"}, {"cdCargo": 6, "cargo": "DEPUTADO FEDERAL", "id": 10001642333, "numero": 1515, "nomeUrna": "JESSICA SALES", "situacao": "APTO", "partido": "MDB"}, {"cdCargo": 10, "cargo": "2\u00ba SUPLENTE", "id": 10001595337, "numero": 500, "nomeUrna": "PEDRO TELES", "situacao": "APTO", "partido": "PSOL"}, {"cdCargo": 6, "cargo": "DEPUTADO FEDERAL", "id": 10001595347, "numero": 5012, "nomeUrna": "WILLIAM FRAN\u00c7A", "situacao": "APTO", "partido": "PSOL"}, {"cdCargo": 7, "cargo": "DEPUTADO ESTADUAL", "id": 10001606216, "numero": 90333, "nomeUrna": "JO\u00c3O DA IDA", "situacao": "APTO", "partido": "PROS"}, {"cdCargo": 7, "cargo": "DEPUTADO ESTADUAL", "id": 10001670856, "numero": 51888, "nomeUrna": "JOSEMIR ANUTE", "situacao": "APTO", "partido": "PATRIOTA"}, {"cdCargo": 6, "cargo": "DEPUTADO FEDERAL", "id": 10001614241, "numero": 3633, "nomeUrna": "Z\u00c9 CARLOS JORNALISTA", "situacao": "APTO", "partido": "AGIR"}, {"cdCargo": 7, "cargo": "DEPUTADO ESTADUAL", "id": 10001649328, "numero": 22777, "nomeUrna": "LABIB", "situacao": "APTO", "partido": "PL"}, {"cdCargo": 6, "cargo": "DEPUTADO FEDERAL", "id": 10001612487, "numero": 4422, "nomeUrna": "CORONEL ULYSSES", "situacao": "APTO", "partido": "UNI\u00c3O"}, {"cdCargo": 6, "cargo": "DEPUTADO FEDERAL", "id": 10001621648, "numero": 1177, "nomeUrna": "GIL TEIXEIRA", "situacao": "APTO", "partido": "PP"}, {"cdCargo": 7, "cargo": "DEPUTADO ESTADUAL", "id": 10001717435, "numero": 27777, "nomeUrna": "MOISES SANTOS O DINO ACRE", "situacao": "APTO", "partido": "DC"}, {"cdCargo": 7, "cargo": "DEPUTADO ESTADUAL", "id": 10001623545, "numero": 44190, "nomeUrna": "CAPIT\u00c3O ESTACIO", "situacao": "APTO", "partido": "UNI\u00c3O"}, {"cdCargo": 7, "cargo": "DEPUTADO ESTADUAL", "id": 10001649309, "numero": 22789, "nomeUrna": "DR LUZIEL CARVALHO", "situacao": "APTO", "partido": "PL"}, {"cdCargo": 7, "cargo": "DEPUTADO ESTADUAL", "id": 10001606493, "numero": 36666, "nomeUrna": "BEN\u00c9 LIMA", "situacao": "APTO", "partido": "AGIR"}, {"cdCargo": 7, "cargo": "DEPUTADO ESTADUAL", "id": 10001649329, "numero": 22222, "nomeUrna": "WANIA PINHEIRO", "situacao": "APTO", "partido": "PL"}, {"cdCargo": 7, "cargo": "DEPUTADO ESTADUAL", "id": 10001650030, "numero": 19444, "nomeUrna": "ANDR\u00c9 DA DROGA VALE", "situacao": "APTO", "partido": "PODE"}, {"cdCargo": 7, "cargo": "DEPUTADO ESTADUAL", "id": 10001649310, "numero": 22223, "nomeUrna": "AFONSO FERNANDES", "situacao": "APTO", "partido": "PL"}, {"cdCargo": 7, "cargo": "DEPUTADO ESTADUAL", "id": 10001643857, "numero": 77070, "nomeUrna": "PASTORA REGIANE MACIEL", "situacao": "APTO", "partido": "SOLIDARIEDADE"}, {"cdCargo": 7, "cargo": "DEPUTADO ESTADUAL", "id": 10001635775, "numero": 65654, "nomeUrna": "WAL", "situacao": "APTO", "partido": "PC do B"}, {"cdCargo": 7, "cargo": "DEPUTADO ESTADUAL", "id": 10001635527, "numero": 10822, "nomeUrna": "ALEXANDRE FERNANDES", "situacao": "APTO", "partido": "REPUBLICANOS"}, {"cdCargo": 5, "cargo": "SENADOR", "id": 10001714547, "numero": 444, "nomeUrna": "ALAN RICK", "situacao": "APTO", "partido": "UNI\u00c3O"}, {"cdCargo": 6, "cargo": "DEPUTADO FEDERAL", "id": 10001595344, "numero": 5020, "nomeUrna": "PROFESSOR ROG\u00c9RIO", "situacao": "APTO", "partido": "PSOL"}, {"cdCargo": 6, "cargo": "DEPUTADO FEDERAL", "id": 10001716340, "numero": 4511, "nomeUrna": "NORMANDO SALES", "situacao": "APTO", "partido": "PSDB"}, {"cdCargo": 6, "cargo": "DEPUTADO FEDERAL", "id": 10001612488, "numero": 4444, "nomeUrna": "DR FABIO RUEDA", "situacao": "APTO", "partido": "UNI\u00c3O"}, {"cdCargo": 7, "cargo": "DEPUTADO ESTADUAL", "id": 10001595364, "numero": 50001, "nomeUrna": "NILCEMIR CALAFATE", "situacao": "APTO", "partido": "PSOL"}, {"cdCargo": 7, "cargo": "DEPUTADO ESTADUAL", "id": 10001600522, "numero": 50033, "nomeUrna": "MARIA PERPETUO", "situacao": "APTO", "partido": "PSOL"}, {"cdCargo": 7, "cargo": "DEPUTADO ESTADUAL", "id": 10001635531, "numero": 10456, "nomeUrna": "TADEU HASSEM", "situacao": "APTO", "partido": "REPUBLICANOS"}, {"cdCargo": 7, "cargo": "DEPUTADO ESTADUAL", "id": 10001622768, "numero": 12200, "nomeUrna": "LEOPARDO YAWA BANE", "situacao": "APTO", "partido": "PDT"}, {"cdCargo": 6, "cargo": "DEPUTADO FEDERAL", "id": 10001612492, "numero": 4417, "nomeUrna": "PEDRO VALERIO", "situacao": "APTO", "partido": "UNI\u00c3O"}, {"cdCargo": 3, "cargo": "GOVERNADOR", "id": 10001601556, "numero": 55, "nomeUrna": "PETEC\u00c3O", "situacao": "APTO", "partido": "PSD"}, {"cdCargo": 7, "cargo": "DEPUTADO ESTADUAL", "id": 10001643318, "numero": 40456, "nomeUrna": "ADAL\u00cdCIO J\u00daNIOR", "situacao": "APTO", "partido": "PSB"}, {"cdCargo": 7, "cargo": "DEPUTADO ESTADUAL", "id": 10001643426, "numero": 11333, "nomeUrna": "JENNIFER OLIVEIRA", "situacao": "APTO", "partido": "PP"}, {"cdCargo": 6, "cargo": "DEPUTADO FEDERAL", "id": 10001643704, "numero": 7737, "nomeUrna": "DAMAIRA AGUIAR", "situacao": "APTO", "partido": "SOLIDARIEDADE"}, {"cdCargo": 6, "cargo": "DEPUTADO FEDERAL", "id": 10001613551, "numero": 1312, "nomeUrna": "HENRY NOGUEIRA", "situacao": "APTO", "partido": "PT"}, {"cdCargo": 6, "cargo": "DEPUTADO FEDERAL", "id": 10001619994, "numero": 1080, "nomeUrna": "ISRAEL MILANI", "situacao": "APTO", "partido": "REPUBLICANOS"}, {"cdCargo": 6, "cargo": "DEPUTADO FEDERAL", "id": 10001621644, "numero": 1133, "nomeUrna": "SOCORRO FORMIGA", "situacao": "APTO", "partido": "PP"}, {"cdCargo": 7, "cargo": "DEPUTADO ESTADUAL", "id": 10001643842, "numero": 77355, "nomeUrna": "LAUANA ARAUJO", "situacao": "APTO", "partido": "SOLIDARIEDADE"}, {"cdCargo": 7, "cargo": "DEPUTADO ESTADUAL", "id": 10001723798, "numero": 45888, "nomeUrna": "TIAGO MARTINS", "situacao": "APTO", "partido": "PSDB"}, {"cdCargo": 7, "cargo": "DEPUTADO ESTADUAL", "id": 10001643851, "numero": 77567, "nomeUrna": "MANOEL MACHADO", "situacao": "APTO", "partido": "SOLIDARIEDADE"}, {"cdCargo": 6, "cargo": "DEPUTADO FEDERAL", "id": 10001643696, "numero": 7712, "nomeUrna": "MIRLA CESAR", "situacao": "APTO", "partido": "SOLIDARIEDADE"}, {"cdCargo": 7, "cargo": "DEPUTADO ESTADUAL", "id": 10001622772, "numero": 12456, "nomeUrna": "CHICO VIGA", "situacao": "APTO", "partido": "PDT"}, {"cdCargo": 7, "cargo": "DEPUTADO ESTADUAL", "id": 10001606501, "numero": 36200, "nomeUrna": "AMBROZIO MOURA", "situacao": "APTO", "partido": "AGIR"}, {"cdCargo": 4, "cargo": "VICE-GOVERNADOR", "id": 10001606308, "numero": 36, "nomeUrna": "JORGIENE CARNEIRO", "situacao": "APTO", "partido": "AGIR"}, {"cdCargo": 5, "cargo": "SENADOR", "id": 10001606585, "numero": 364, "nomeUrna": "DIMAS SANDAS", "situacao": "APTO", "partido": "AGIR"}, {"cdCargo": 6, "cargo": "DEPUTADO FEDERAL", "id": 10001612485, "numero": 4411, "nomeUrna": "CORONEL EMILIO", "situacao": "APTO", "partido": "UNI\u00c3O"}, {"cdCargo": 7, "cargo": "DEPUTADO ESTADUAL", "id": 10001606512, "numero": 36100, "nomeUrna": "JOYCE DOS BURACOS", "situacao": "APTO", "partido": "AGIR"}, {"cdCargo": 7, "cargo": "DEPUTADO ESTADUAL", "id": 10001643321, "numero": 40444, "nomeUrna": "DR. MARCELO PIMENTA", "situacao": "APTO", "partido": "PSB"}, {"cdCargo": 6, "cargo": "DEPUTADO FEDERAL", "id": 10001621651, "numero": 1144, "nomeUrna": "DR EDSON", "situacao": "APTO", "partido": "PP"}, {"cdCargo": 7, "cargo": "DEPUTADO ESTADUAL", "id": 10001622766, "numero": 12012, "nomeUrna": "RODRIGO SEGUNDO DISTRITO", "situacao": "APTO", "partido": "PDT"}, {"cdCargo": 7, "cargo": "DEPUTADO ESTADUAL", "id": 10001643329, "numero": 40003, "nomeUrna": "CARLITA SOUZA", "situacao": "APTO", "partido": "PSB"}, {"cdCargo": 6, "cargo": "DEPUTADO FEDERAL", "id": 10001716346, "numero": 4500, "nomeUrna": "MINORU KINPARA", "situacao": "APTO", "partido": "PSDB"}, {"cdCargo": 7, "cargo": "DEPUTADO ESTADUAL", "id": 10001622780, "numero": 12612, "nomeUrna": "F\u00c1BIO ARA\u00daJO", "situacao": "APTO", "partido": "PDT"}, {"cdCargo": 6, "cargo": "DEPUTADO FEDERAL", "id": 10001595343, "numero": 5011, "nomeUrna": "C\u00c9LIO ROCHA", "situacao": "APTO", "partido": "PSOL"}, {"cdCargo": 7, "cargo": "DEPUTADO ESTADUAL", "id": 10001635781, "numero": 13012, "nomeUrna": "FABINHO", "situacao": "APTO", "partido": "PT"}, {"cdCargo": 7, "cargo": "DEPUTADO ESTADUAL", "id": 10001649312, "numero": 22500, "nomeUrna": "TARCISIO PINHEIRO", "situacao": "APTO", "partido": "PL"}, {"cdCargo": 7, "cargo": "DEPUTADO ESTADUAL", "id": 10001601423, "numero": 55321, "nomeUrna": "DELEGADO JUDSON", "situacao": "APTO", "partido": "PSD"}, {"cdCargo": 7, "cargo": "DEPUTADO ESTADUAL", "id": 10001623549, "numero": 44222, "nomeUrna": "NABUCO SILVA", "situacao": "APTO", "partido": "UNI\u00c3O"}, {"cdCargo": 7, "cargo": "DEPUTADO ESTADUAL", "id": 10001635539, "numero": 10111, "nomeUrna": "GENE DINIZ", "situacao": "APTO", "partido": "REPUBLICANOS"}, {"cdCargo": 7, "cargo": "DEPUTADO ESTADUAL", "id": 10001643441, "numero": 11155, "nomeUrna": "BIGODE", "situacao": "APTO", "partido": "PP"}, {"cdCargo": 7, "cargo": "DEPUTADO ESTADUAL", "id": 10001649327, "numero": 22122, "nomeUrna": "ISMAEL MUNIZ", "situacao": "APTO", "partido": "PL"}, {"cdCargo": 4, "cargo": "VICE-GOVERNADOR", "id": 10001639520, "numero": 15, "nomeUrna": "FERNANDO ZAMORA", "situacao": "APTO", "partido": "PRTB"}, {"cdCargo": 7, "cargo": "DEPUTADO ESTADUAL", "id": 10001723808, "numero": 23033, "nomeUrna": "TEREZINHA", "situacao": "APTO", "partido": "CIDADANIA"}, {"cdCargo": 9, "cargo": "1\u00ba SUPLENTE", "id": 10001595338, "numero": 500, "nomeUrna": "AUGUSTO MAIA", "situacao": "APTO", "partido": "PSOL"}, {"cdCargo": 7, "cargo": "DEPUTADO ESTADUAL", "id": 10001730224, "numero": 51001, "nomeUrna": "ALEXANDRINA VASQUES", "situacao": "APTO", "partido": "PATRIOTA"}, {"cdCargo": 7, "cargo": "DEPUTADO ESTADUAL", "id": 10001723788, "numero": 45190, "nomeUrna": "SGT CADMIEL BOMFIM", "situacao": "APTO", "partido": "PSDB"}, {"cdCargo": 7, "cargo": "DEPUTADO ESTADUAL", "id": 10001623539, "numero": 44007, "nomeUrna": "MINEIRINHO", "situacao": "APTO", "partido": "UNI\u00c3O"}, {"cdCargo": 7, "cargo": "DEPUTADO ESTADUAL", "id": 10001622771, "numero": 12777, "nomeUrna": "DELEGADA CARLA BRITTO", "situacao": "APTO", "partido": "PDT"}, {"cdCargo": 7, "cargo": "DEPUTADO ESTADUAL", "id": 10001623554, "numero": 44700, "nomeUrna": "DRA CAROL", "situacao": "APTO", "partido": "UNI\u00c3O"}, {"cdCargo": 7, "cargo": "DEPUTADO ESTADUAL", "id": 10001732898, "numero": 15001, "nomeUrna": "KELLY CRISTINA", "situacao": "APTO", "partido": "MDB"}, {"cdCargo": 7, "cargo": "DEPUTADO ESTADUAL", "id": 10001622773, "numero": 12444, "nomeUrna": "ITAMIR LIMA", "situacao": "APTO", "partido": "PDT"}, {"cdCargo": 7, "cargo": "DEPUTADO ESTADUAL", "id": 10001635778, "numero": 13123, "nomeUrna": "DANIEL ZEN", "situacao": "APTO", "partido": "PT"}, {"cdCargo": 7, "cargo": "DEPUTADO ESTADUAL", "id": 10001606207, "numero": 90345, "nomeUrna": "SOUZA SOMBRA", "situacao": "APTO", "partido": "PROS"}, {"cdCargo": 7, "cargo": "DEPUTADO ESTADUAL", "id": 10001622774, "numero": 12287, "nomeUrna": "MEIRY OLIVEIRA", "situacao": "APTO", "partido": "PDT"}, {"cdCargo": 6, "cargo": "DEPUTADO FEDERAL", "id": 10001649415, "numero": 4077, "nomeUrna": "PROFESSORA ROSINEIA FROTA ", "situacao": "APTO", "partido": "PSB"}, {"cdCargo": 7, "cargo": "DEPUTADO ESTADUAL", "id": 10001595354, "numero": 50100, "nomeUrna": "MAGUILA", "situacao": "APTO", "partido": "PSOL"}, {"cdCargo": 7, "cargo": "DEPUTADO ESTADUAL", "id": 10001635784, "numero": 13000, "nomeUrna": "CHARLES BRASIL", "situacao": "APTO", "partido": "PT"}, {"cdCargo": 7, "cargo": "DEPUTADO ESTADUAL", "id": 10001606511, "numero": 36008, "nomeUrna": "EVANDRO CANTOR", "situacao": "APTO", "partido": "AGIR"}, {"cdCargo": 3, "cargo": "GOVERNADOR", "id": 10001616169, "numero": 13, "nomeUrna": "JORGE VIANA", "situacao": "APTO", "partido": "PT"}, {"cdCargo": 7, "cargo": "DEPUTADO ESTADUAL", "id": 10001643852, "numero": 77777, "nomeUrna": "DR. LUCAS ESMYTH", "situacao": "APTO", "partido": "SOLIDARIEDADE"}, {"cdCargo": 7, "cargo": "DEPUTADO ESTADUAL", "id": 10001623546, "numero": 44333, "nomeUrna": "VANIO MIRANDA", "situacao": "APTO", "partido": "UNI\u00c3O"}, {"cdCargo": 7, "cargo": "DEPUTADO ESTADUAL", "id": 10001643859, "numero": 77987, "nomeUrna": "SIDA DO MERCANTIL S\u00c3O PAULO ", "situacao": "APTO", "partido": "SOLIDARIEDADE"}, {"cdCargo": 7, "cargo": "DEPUTADO ESTADUAL", "id": 10001606215, "numero": 90852, "nomeUrna": "JECSON DUTRA", "situacao": "APTO", "partido": "PROS"}, {"cdCargo": 7, "cargo": "DEPUTADO ESTADUAL", "id": 10001650032, "numero": 19123, "nomeUrna": "NEN\u00c9M ALMEIDA", "situacao": "APTO", "partido": "PODE"}, {"cdCargo": 6, "cargo": "DEPUTADO FEDERAL", "id": 10001614247, "numero": 3600, "nomeUrna": "UZIR SANTOS", "situacao": "APTO", "partido": "AGIR"}, {"cdCargo": 7, "cargo": "DEPUTADO ESTADUAL", "id": 10001622761, "numero": 12123, "nomeUrna": "TCH\u00ca", "situacao": "APTO", "partido": "PDT"}, {"cdCargo": 7, "cargo": "DEPUTADO ESTADUAL", "id": 10001595362, "numero": 50999, "nomeUrna": "M\u00d4NICA DINIZ", "situacao": "APTO", "partido": "PSOL"}, {"cdCargo": 7, "cargo": "DEPUTADO ESTADUAL", "id": 10001601424, "numero": 55512, "nomeUrna": "DR WELBER DE LIMA", "situacao": "APTO", "partido": "PSD"}, {"cdCargo": 6, "cargo": "DEPUTADO FEDERAL", "id": 10001614240, "numero": 3678, "nomeUrna": "PROF COSTA", "situacao": "APTO", "partido": "AGIR"}, {"cdCargo": 7, "cargo": "DEPUTADO ESTADUAL", "id": 10001723794, "numero": 23300, "nomeUrna": "DAVI LIMA", "situacao": "APTO", "partido": "CIDADANIA"}, {"cdCargo": 7, "cargo": "DEPUTADO ESTADUAL", "id": 10001717428, "numero": 27022, "nomeUrna": "MICHEL BOC\u00c3O", "situacao": "APTO", "partido": "DC"}, {"cdCargo": 7, "cargo": "DEPUTADO ESTADUAL", "id": 10001643316, "numero": 40789, "nomeUrna": "BATISTA", "situacao": "APTO", "partido": "PSB"}, {"cdCargo": 7, "cargo": "DEPUTADO ESTADUAL", "id": 10001643854, "numero": 77123, "nomeUrna": "MAJOR MARIO", "situacao": "APTO", "partido": "SOLIDARIEDADE"}, {"cdCargo": 7, "cargo": "DEPUTADO ESTADUAL", "id": 10001635766, "numero": 13333, "nomeUrna": "IDESIO", "situacao": "APTO", "partido": "PT"}, {"cdCargo": 6, "cargo": "DEPUTADO FEDERAL", "id": 10001716344, "numero": 2323, "nomeUrna": "PASTORA ODETE", "situacao": "APTO", "partido": "CIDADANIA"}, {"cdCargo": 7, "cargo": "DEPUTADO ESTADUAL", "id": 10001635540, "numero": 10777, "nomeUrna": "PASTOR WAGNER FELIPE", "situacao": "APTO", "partido": "REPUBLICANOS"}, {"cdCargo": 9, "cargo": "1\u00ba SUPLENTE", "id": 10001643545, "numero": 131, "nomeUrna": "SIB\u00c1 MACHADO", "situacao": "APTO", "partido": "PT"}, {"cdCargo": 7, "cargo": "DEPUTADO ESTADUAL", "id": 10001649319, "numero": 22700, "nomeUrna": "DRA. FABIOLA HELENA", "situacao": "APTO", "partido": "PL"}, {"cdCargo": 7, "cargo": "DEPUTADO ESTADUAL", "id": 10001622775, "numero": 12121, "nomeUrna": "VANESSA FACUNDES", "situacao": "APTO", "partido": "PDT"}, {"cdCargo": 7, "cargo": "DEPUTADO ESTADUAL", "id": 10001670857, "numero": 51111, "nomeUrna": "CARLINHOS UYENO", "situacao": "APTO", "partido": "PATRIOTA"}, {"cdCargo": 6, "cargo": "DEPUTADO FEDERAL", "id": 10001606133, "numero": 9000, "nomeUrna": "MARCOS FABRICIO", "situacao": "APTO", "partido": "PROS"}, {"cdCargo": 7, "cargo": "DEPUTADO ESTADUAL", "id": 10001643319, "numero": 40777, "nomeUrna": "ROMILDO SILVA", "situacao": "APTO", "partido": "PSB"}, {"cdCargo": 7, "cargo": "DEPUTADO ESTADUAL", "id": 10001642325, "numero": 15777, "nomeUrna": "ANDR\u00c9 ARIOSTO", "situacao": "APTO", "partido": "MDB"}, {"cdCargo": 7, "cargo": "DEPUTADO ESTADUAL", "id": 10001606198, "numero": 90899, "nomeUrna": "BRUNA LIMA", "situacao": "APTO", "partido": "PROS"}, {"cdCargo": 6, "cargo": "DEPUTADO FEDERAL", "id": 10001612489, "numero": 4412, "nomeUrna": "HIAMAR PINHEIRO", "situacao": "APTO", "partido": "UNI\u00c3O"}, {"cdCargo": 6, "cargo": "DEPUTADO FEDERAL", "id": 10001655355, "numero": 3355, "nomeUrna": "ROZANA SOUSA", "situacao": "APTO", "partido": "PMN"}, {"cdCargo": 7, "cargo": "DEPUTADO ESTADUAL", "id": 10001643330, "numero": 40555, "nomeUrna": "RAIMUNDA QUEIROZ", "situacao": "APTO", "partido": "PSB"}, {"cdCargo": 7, "cargo": "DEPUTADO ESTADUAL", "id": 10001643314, "numero": 40234, "nomeUrna": "ANTONIO MORAIS", "situacao": "APTO", "partido": "PSB"}, {"cdCargo": 7, "cargo": "DEPUTADO ESTADUAL", "id": 10001642324, "numero": 15151, "nomeUrna": "EDUARDO DIAS", "situacao": "APTO", "partido": "MDB"}, {"cdCargo": 7, "cargo": "DEPUTADO ESTADUAL", "id": 10001643850, "numero": 77456, "nomeUrna": "TAMPINHA BITTAR", "situacao": "APTO", "partido": "SOLIDARIEDADE"}, {"cdCargo": 10, "cargo": "2\u00ba SUPLENTE", "id": 10001731864, "numero": 199, "nomeUrna": "RENNAN BITHS", "situacao": "APTO", "partido": "PDT"}, {"cdCargo": 6, "cargo": "DEPUTADO FEDERAL", "id": 10001642335, "numero": 1569, "nomeUrna": "HAMILTON LIDERAN\u00c7A", "situacao": "APTO", "partido": "MDB"}, {"cdCargo": 3, "cargo": "GOVERNADOR", "id": 10001623440, "numero": 44, "nomeUrna": "MARCIO BITTAR", "situacao": "APTO", "partido": "UNI\u00c3O"}, {"cdCargo": 6, "cargo": "DEPUTADO FEDERAL", "id": 10001601531, "numero": 5533, "nomeUrna": "SUELLEN CARLOS", "situacao": "APTO", "partido": "PSD"}, {"cdCargo": 7, "cargo": "DEPUTADO ESTADUAL", "id": 10001595363, "numero": 50233, "nomeUrna": "LEANDRO CABRAL", "situacao": "APTO", "partido": "PSOL"}, {"cdCargo": 6, "cargo": "DEPUTADO FEDERAL", "id": 10001716342, "numero": 4555, "nomeUrna": "LANNA VAZ", "situacao": "APTO", "partido": "PSDB"}, {"cdCargo": 6, "cargo": "DEPUTADO FEDERAL", "id": 10001601536, "numero": 5577, "nomeUrna": "CLERTON SOUZA", "situacao": "APTO", "partido": "PSD"}, {"cdCargo": 7, "cargo": "DEPUTADO ESTADUAL", "id": 10001642318, "numero": 15456, "nomeUrna": "MAZ\u00c9 RAMOS", "situacao": "APTO", "partido": "MDB"}, {"cdCargo": 6, "cargo": "DEPUTADO FEDERAL", "id": 10001643699, "numero": 7770, "nomeUrna": "ISNAILDA", "situacao": "APTO", "partido": "SOLIDARIEDADE"}, {"cdCargo": 7, "cargo": "DEPUTADO ESTADUAL", "id": 10001622777, "numero": 12159, "nomeUrna": "ALMINERES DO ELDORADO", "situacao": "APTO", "partido": "PDT"}, {"cdCargo": 6, "cargo": "DEPUTADO FEDERAL", "id": 10001724875, "numero": 1505, "nomeUrna": "EDITH MONTES", "situacao": "APTO", "partido": "MDB"}, {"cdCargo": 7, "cargo": "DEPUTADO ESTADUAL", "id": 10001601440, "numero": 55552, "nomeUrna": "NAZAR\u00c9 DA RODA VIVA", "situacao": "APTO", "partido": "PSD"}, {"cdCargo": 7, "cargo": "DEPUTADO ESTADUAL", "id": 10001649308, "numero": 22190, "nomeUrna": "IGOR OLIVEIRA", "situacao": "APTO", "partido": "PL"}, {"cdCargo": 7, "cargo": "DEPUTADO ESTADUAL", "id": 10001623536, "numero": 44200, "nomeUrna": "JOAO DE DEUS", "situacao": "APTO", "partido": "UNI\u00c3O"}, {"cdCargo": 7, "cargo": "DEPUTADO ESTADUAL", "id": 10001723807, "numero": 45123, "nomeUrna": "RUDILEI ESTRELA ", "situacao": "APTO", "partido": "PSDB"}, {"cdCargo": 7, "cargo": "DEPUTADO ESTADUAL", "id": 10001606221, "numero": 90900, "nomeUrna": "MAYARA FARIAS", "situacao": "APTO", "partido": "PROS"}, {"cdCargo": 7, "cargo": "DEPUTADO ESTADUAL", "id": 10001650024, "numero": 19191, "nomeUrna": "JUNIOR TOMAZ", "situacao": "APTO", "partido": "PODE"}, {"cdCargo": 7, "cargo": "DEPUTADO ESTADUAL", "id": 10001670860, "numero": 51777, "nomeUrna": "UENA PAULA", "situacao": "APTO", "partido": "PATRIOTA"}, {"cdCargo": 7, "cargo": "DEPUTADO ESTADUAL", "id": 10001606509, "numero": 36461, "nomeUrna": "ADRIANA ANDRADE", "situacao": "APTO", "partido": "AGIR"}, {"cdCargo": 6, "cargo": "DEPUTADO FEDERAL", "id": 10001601535, "numero": 5523, "nomeUrna": "ROSANA NASCIMENTO", "situacao": "APTO", "partido": "PSD"}, {"cdCargo": 7, "cargo": "DEPUTADO ESTADUAL", "id": 10001606510, "numero": 36789, "nomeUrna": "PROFESSOR TONNY", "situacao": "APTO", "partido": "AGIR"}, {"cdCargo": 7, "cargo": "DEPUTADO ESTADUAL", "id": 10001643428, "numero": 11122, "nomeUrna": "NICOLAU JUNIOR", "situacao": "APTO", "partido": "PP"}, {"cdCargo": 7, "cargo": "DEPUTADO ESTADUAL", "id": 10001649315, "numero": 22678, "nomeUrna": "ROSE DA ENDEMIAS", "situacao": "APTO", "partido": "PL"}, {"cdCargo": 6, "cargo": "DEPUTADO FEDERAL", "id": 10001670870, "numero": 5123, "nomeUrna": "REGINA DUTRA", "situacao": "APTO", "partido": "PATRIOTA"}, {"cdCargo": 7, "cargo": "DEPUTADO ESTADUAL", "id": 10001650027, "numero": 19222, "nomeUrna": "ADEKSON LIMA", "situacao": "APTO", "partido": "PODE"}, {"cdCargo": 7, "cargo": "DEPUTADO ESTADUAL", "id": 10001635780, "numero": 13013, "nomeUrna": "CES\u00c1RIO BRAGA", "situacao": "APTO", "partido": "PT"}, {"cdCargo": 7, "cargo": "DEPUTADO ESTADUAL", "id": 10001643322, "numero": 40123, "nomeUrna": "ISAAC RONALTTI", "situacao": "APTO", "partido": "PSB"}, {"cdCargo": 3, "cargo": "GOVERNADOR", "id": 10001595336, "numero": 50, "nomeUrna": "PROFESSOR NILSON", "situacao": "APTO", "partido": "PSOL"}, {"cdCargo": 7, "cargo": "DEPUTADO ESTADUAL", "id": 10001643442, "numero": 11222, "nomeUrna": "RICHARD ROCHA", "situacao": "APTO", "partido": "PP"}, {"cdCargo": 6, "cargo": "DEPUTADO FEDERAL", "id": 10001649411, "numero": 4040, "nomeUrna": "DR THOR DANTAS", "situacao": "APTO", "partido": "PSB"}, {"cdCargo": 7, "cargo": "DEPUTADO ESTADUAL", "id": 10001606197, "numero": 90142, "nomeUrna": "FRANCISCO ARA\u00daJO", "situacao": "APTO", "partido": "PROS"}, {"cdCargo": 7, "cargo": "DEPUTADO ESTADUAL", "id": 10001606508, "numero": 36400, "nomeUrna": "RAI HOLANDA", "situacao": "APTO", "partido": "AGIR"}, {"cdCargo": 7, "cargo": "DEPUTADO ESTADUAL", "id": 10001635528, "numero": 10100, "nomeUrna": "CLAUDINHA", "situacao": "APTO", "partido": "REPUBLICANOS"}, {"cdCargo": 7, "cargo": "DEPUTADO ESTADUAL", "id": 10001723805, "numero": 23233, "nomeUrna": "ELIZABETE", "situacao": "APTO", "partido": "CIDADANIA"}, {"cdCargo": 6, "cargo": "DEPUTADO FEDERAL", "id": 10001642338, "numero": 1568, "nomeUrna": "JEFFERSON MONTEIRO SOARES", "situacao": "APTO", "partido": "MDB"}, {"cdCargo": 7, "cargo": "DEPUTADO ESTADUAL", "id": 10001642323, "numero": 15120, "nomeUrna": "WIRTO DA BAIXADA", "situacao": "APTO", "partido": "MDB"}, {"cdCargo": 7, "cargo": "DEPUTADO ESTADUAL", "id": 10001649321, "numero": 22007, "nomeUrna": "TEREZINHA ARAUJO", "situacao": "APTO", "partido": "PL"}, {"cdCargo": 7, "cargo": "DEPUTADO ESTADUAL", "id": 10001643435, "numero": 11257, "nomeUrna": "PASTOR MAANAIM", "situacao": "APTO", "partido": "PP"}, {"cdCargo": 7, "cargo": "DEPUTADO ESTADUAL", "id": 10001635782, "numero": 13444, "nomeUrna": "MARIA VAI COM AS OUTRAS", "situacao": "APTO", "partido": "PT"}, {"cdCargo": 7, "cargo": "DEPUTADO ESTADUAL", "id": 10001606210, "numero": 90456, "nomeUrna": "VILSEU FERREIRA", "situacao": "APTO", "partido": "PROS"}, {"cdCargo": 6, "cargo": "DEPUTADO FEDERAL", "id": 10001621646, "numero": 1122, "nomeUrna": "ZEZINHO BARBARY", "situacao": "APTO", "partido": "PP"}]